Workbook
Name IQ_CH: 110000
Name IQ_CQ: 5000
Name IQ_CY: 10000
Name IQ_DAILY: 500000
Name IQ_FH: 100000
Name IQ_FQ: 500
Name IQ_FY: 1000
Name IQ_LTM: 2000
Name IQ_MONTH: 15000
Name IQ_NTM: 6000
Name IQ_WEEK: 50000
Name IQ_YTD: 3000

Sheet ConsolidatedResponses
A1: Supplier Name | B1: Source Language | C1: Service type | D1: Language | E1: Structure | F1: Release Platform | G1: Standard + Rate | H1: Standard Rate | I1: Batched Rate | J1: Rush Charge 1 | K1: Rush Charge 2 | L1: Additional Discount Offering Description | M1: % Discount Offered | N1: Notes / Additional Assumptions
A2: ='Summary (READ FIRST)'!$B$8 -> Supplier 1 | B2: ='Summary (READ FIRST)'!$B$11 -> English | C2: Subtitling | D2: Aymara | E2: FEATURE | F2: THEATRICAL RELEASE | G2: =Subtitling!E12 -> 26 | H2: =Subtitling!F12 -> 16 | J2: =Subtitling!$W$12 -> 1 | K2: =Subtitling!$X$12 -> 0.5 | L2: =Subtitling!$Z$12 -> Tools | M2: =Subtitling!$AA$12 -> 0.15 | N2: =Subtitling!$AB$12 -> Note 1
A3: ='Summary (READ FIRST)'!$B$8 -> Supplier 1 | B3: ='Summary (READ FIRST)'!$B$11 -> English | C3: Subtitling | D3: Aymara | E3: FEATURE | F3: NON-THEATRICAL - HOME ENT/STREAMING | G3: =Subtitling!H12 -> 28 | H3: =Subtitling!I12 -> 25 | J3: =Subtitling!$W$12 -> 1 | K3: =Subtitling!$X$12 -> 0.5 | L3: =Subtitling!$Z$12 -> Tools | M3: =Subtitling!$AA$12 -> 0.15 | N3: =Subtitling!$AB$12 -> Note 1
A4: ='Summary (READ FIRST)'!$B$8 -> Supplier 1 | B4: ='Summary (READ FIRST)'!$B$11 -> English | C4: Subtitling | D4: Aymara | E4: FEATURE | F4: NON-THEATRICAL - LINEAR BROADCAST | G4: =Subtitling!K12 -> 22 | H4: =Subtitling!L12 -> 10 | J4: =Subtitling!$W$12 -> 1 | K4: =Subtitling!$X$12 -> 0.5 | L4: =Subtitling!$Z$12 -> Tools | M4: =Subtitling!$AA$12 -> 0.15 | N4: =Subtitling!$AB$12 -> Note 1
A5: ='Summary (READ FIRST)'!$B$8 -> Supplier 1 | B5: ='Summary (READ FIRST)'!$B$11 -> English | C5: Subtitling | D5: Aymara | E5: EPISODIC | F5: HOME ENT/STREAMING | G5: =Subtitling!N12 -> 23 | H5: =Subtitling!O12 -> 17 | J5: =Subtitling!$W$12 -> 1 | K5: =Subtitling!$X$12 -> 0.5 | L5: =Subtitling!$Z$12 -> Tools | M5: =Subtitling!$AA$12 -> 0.15 | N5: =Subtitling!$AB$12 -> Note 1
A6: ='Summary (READ FIRST)'!$B$8 -> Supplier 1 | B6: ='Summary (READ FIRST)'!$B$11 -> English | C6: Subtitling | D6: Aymara | E6: EPISODIC | F6: BROADCAST/LINEAR | G6: =Subtitling!Q12 -> 34 | H6: =Subtitling!R12 -> 0 | J6: =Subtitling!$W$12 -> 1 | K6: =Subtitling!$X$12 -> 0.5 | L6: =Subtitling!$Z$12 -> Tools | M6: =Subtitling!$AA$12 -> 0.15 | N6: =Subtitling!$AB$12 -> Note 1
A7: ='Summary (READ FIRST)'!$B$8 -> Supplier 1 | B7: ='Summary (READ FIRST)'!$B$11 -> English | C7: Subtitling | D7: Aymara | E7: EPISODIC | F7: DISCOVERY/NON-SCRIPTED | G7: =Subtitling!T12 -> 19 | H7: =Subtitling!U12 -> 9 | J7: =Subtitling!$W$12 -> 1 | K7: =Subtitling!$X$12 -> 0.5 | L7: =Subtitling!$Z$12 -> Tools | M7: =Subtitling!$AA$12 -> 0.15 | N7: =Subtitling!$AB$12 -> Note 1
A8: ='Summary (READ FIRST)'!$B$8 -> Supplier 1 | B8: ='Summary (READ FIRST)'!$B$11 -> English | C8: Subtitling | D8: Mayan | E8: FEATURE | F8: THEATRICAL RELEASE | G8: =Subtitling!E13 -> 20 | H8: =Subtitling!F13 -> 8 | J8: =Subtitling!$W$13 -> 1 | K8: =Subtitling!$X$13 -> 0.5 | L8: =Subtitling!$Z$13 -> Workflow | M8: =Subtitling!$AA$13 -> 0 | N8: =Subtitling!$AB$13 -> 0
A9: ='Summary (READ FIRST)'!$B$8 -> Supplier 1 | B9: ='Summary (READ FIRST)'!$B$11 -> English | C9: Subtitling | D9: Mayan | E9: FEATURE | F9: NON-THEATRICAL - HOME ENT/STREAMING | G9: =Subtitling!H13 -> 21 | H9: =Subtitling!I13 -> 16 | J9: =Subtitling!$W$13 -> 1 | K9: =Subtitling!$X$13 -> 0.5 | L9: =Subtitling!$Z$13 -> Workflow | M9: =Subtitling!$AA$13 -> 0 | N9: =Subtitling!$AB$13 -> 0
A10: ='Summary (READ FIRST)'!$B$8 -> Supplier 1 | B10: ='Summary (READ FIRST)'!$B$11 -> English | C10: Subtitling | D10: Mayan | E10: FEATURE | F10: NON-THEATRICAL - LINEAR BROADCAST | G10: =Subtitling!K13 -> 0 | H10: =Subtitling!L13 -> 12 | J10: =Subtitling!$W$13 -> 1 | K10: =Subtitling!$X$13 -> 0.5 | L10: =Subtitling!$Z$13 -> Workflow | M10: =Subtitling!$AA$13 -> 0 | N10: =Subtitling!$AB$13 -> 0
A11: ='Summary (READ FIRST)'!$B$8 -> Supplier 1 | B11: ='Summary (READ FIRST)'!$B$11 -> English | C11: Subtitling | D11: Mayan | E11: EPISODIC | F11: HOME ENT/STREAMING | G11: =Subtitling!N13 -> 0 | H11: =Subtitling!O13 -> 17 | J11: =Subtitling!$W$13 -> 1 | K11: =Subtitling!$X$13 -> 0.5 | L11: =Subtitling!$Z$13 -> Workflow | M11: =Subtitling!$AA$13 -> 0 | N11: =Subtitling!$AB$13 -> 0
A12: ='Summary (READ FIRST)'!$B$8 -> Supplier 1 | B12: ='Summary (READ FIRST)'!$B$11 -> English | C12: Subtitling | D12: Mayan | E12: EPISODIC | F12: BROADCAST/LINEAR | G12: =Subtitling!Q13 -> 27 | H12: =Subtitling!R13 -> 20 | J12: =Subtitling!$W$13 -> 1 | K12: =Subtitling!$X$13 -> 0.5 | L12: =Subtitling!$Z$13 -> Workflow | M12: =Subtitling!$AA$13 -> 0 | N12: =Subtitling!$AB$13 -> 0
A13: ='Summary (READ FIRST)'!$B$8 -> Supplier 1 | B13: ='Summary (READ FIRST)'!$B$11 -> English | C13: Subtitling | D13: Mayan | E13: EPISODIC | F13: DISCOVERY/NON-SCRIPTED | G13: =Subtitling!T13 -> 0 | H13: =Subtitling!U13 -> 12 | J13: =Subtitling!$W$13 -> 1 | K13: =Subtitling!$X$13 -> 0.5 | L13: =Subtitling!$Z$13 -> Workflow | M13: =Subtitling!$AA$13 -> 0 | N13: =Subtitling!$AB$13 -> 0
A14: ='Summary (READ FIRST)'!$B$8 -> Supplier 1 | B14: ='Summary (READ FIRST)'!$B$11 -> English | C14: Subtitling | D14: Portuguese (Brazil) | E14: FEATURE | F14: THEATRICAL RELEASE | G14: =Subtitling!E14 -> 0 | H14: =Subtitling!F14 -> 21 | J14: =Subtitling!$W$14 -> 0 | K14: =Subtitling!$X$14 -> 0 | L14: =Subtitling!$Z$14 -> 0 | M14: =Subtitling!$AA$14 -> 0.2 | N14: =Subtitling!$AB$14 -> 0
A15: ='Summary (READ FIRST)'!$B$8 -> Supplier 1 | B15: ='Summary (READ FIRST)'!$B$11 -> English | C15: Subtitling | D15: Portuguese (Brazil) | E15: FEATURE | F15: NON-THEATRICAL - HOME ENT/STREAMING | G15: =Subtitling!H14 -> 27 | H15: =Subtitling!I14 -> 18 | J15: =Subtitling!$W$14 -> 0 | K15: =Subtitling!$X$14 -> 0 | L15: =Subtitling!$Z$14 -> 0 | M15: =Subtitling!$AA$14 -> 0.2 | N15: =Subtitling!$AB$14 -> 0
A16: ='Summary (READ FIRST)'!$B$8 -> Supplier 1 | B16: ='Summary (READ FIRST)'!$B$11 -> English | C16: Subtitling | D16: Portuguese (Brazil) | E16: FEATURE | F16: NON-THEATRICAL - LINEAR BROADCAST | G16: =Subtitling!K14 -> 38 | H16: =Subtitling!L14 -> 24 | J16: =Subtitling!$W$14 -> 0 | K16: =Subtitling!$X$14 -> 0 | L16: =Subtitling!$Z$14 -> 0 | M16: =Subtitling!$AA$14 -> 0.2 | N16: =Subtitling!$AB$14 -> 0
A17: ='Summary (READ FIRST)'!$B$8 -> Supplier 1 | B17: ='Summary (READ FIRST)'!$B$11 -> English | C17: Subtitling | D17: Portuguese (Brazil) | E17: EPISODIC | F17: HOME ENT/STREAMING | G17: =Subtitling!N14 -> 38 | H17: =Subtitling!O14 -> 21 | J17: =Subtitling!$W$14 -> 0 | K17: =Subtitling!$X$14 -> 0 | L17: =Subtitling!$Z$14 -> 0 | M17: =Subtitling!$AA$14 -> 0.2 | N17: =Subtitling!$AB$14 -> 0
A18: ='Summary (READ FIRST)'!$B$8 -> Supplier 1 | B18: ='Summary (READ FIRST)'!$B$11 -> English | C18: Subtitling | D18: Portuguese (Brazil) | E18: EPISODIC | F18: BROADCAST/LINEAR | G18: =Subtitling!Q14 -> 0 | H18: =Subtitling!R14 -> 19 | J18: =Subtitling!$W$14 -> 0 | K18: =Subtitling!$X$14 -> 0 | L18: =Subtitling!$Z$14 -> 0 | M18: =Subtitling!$AA$14 -> 0.2 | N18: =Subtitling!$AB$14 -> 0
A19: ='Summary (READ FIRST)'!$B$8 -> Supplier 1 | B19: ='Summary (READ FIRST)'!$B$11 -> English | C19: Subtitling | D19: Portuguese (Brazil) | E19: EPISODIC | F19: DISCOVERY/NON-SCRIPTED | G19: =Subtitling!T14 -> 21 | H19: =Subtitling!U14 -> 0 | J19: =Subtitling!$W$14 -> 0 | K19: =Subtitling!$X$14 -> 0 | L19: =Subtitling!$Z$14 -> 0 | M19: =Subtitling!$AA$14 -> 0.2 | N19: =Subtitling!$AB$14 -> 0
A20: ='Summary (READ FIRST)'!$B$8 -> Supplier 1 | B20: ='Summary (READ FIRST)'!$B$11 -> English | C20: Subtitling | D20: Quechua | E20: FEATURE | F20: THEATRICAL RELEASE | G20: =Subtitling!E15 -> 27 | H20: =Subtitling!F15 -> 22 | J20: =Subtitling!$W$15 -> 1 | K20: =Subtitling!$X$15 -> 0.5 | L20: =Subtitling!$Z$15 -> Tools | M20: =Subtitling!$AA$15 -> 0.05 | N20: =Subtitling!$AB$15 -> Note 1
A21: ='Summary (READ FIRST)'!$B$8 -> Supplier 1 | B21: ='Summary (READ FIRST)'!$B$11 -> English | C21: Subtitling | D21: Quechua | E21: FEATURE | F21: NON-THEATRICAL - HOME ENT/STREAMING | G21: =Subtitling!H15 -> 27 | H21: =Subtitling!I15 -> 23 | J21: =Subtitling!$W$15 -> 1 | K21: =Subtitling!$X$15 -> 0.5 | L21: =Subtitling!$Z$15 -> Tools | M21: =Subtitling!$AA$15 -> 0.05 | N21: =Subtitling!$AB$15 -> Note 1
A22: ='Summary (READ FIRST)'!$B$8 -> Supplier 1 | B22: ='Summary (READ FIRST)'!$B$11 -> English | C22: Subtitling | D22: Quechua | E22: FEATURE | F22: NON-THEATRICAL - LINEAR BROADCAST | G22: =Subtitling!K15 -> 36 | H22: =Subtitling!L15 -> 20 | J22: =Subtitling!$W$15 -> 1 | K22: =Subtitling!$X$15 -> 0.5 | L22: =Subtitling!$Z$15 -> Tools | M22: =Subtitling!$AA$15 -> 0.05 | N22: =Subtitling!$AB$15 -> Note 1
A23: ='Summary (READ FIRST)'!$B$8 -> Supplier 1 | B23: ='Summary (READ FIRST)'!$B$11 -> English | C23: Subtitling | D23: Quechua | E23: EPISODIC | F23: HOME ENT/STREAMING | G23: =Subtitling!N15 -> 0 | H23: =Subtitling!O15 -> 15 | J23: =Subtitling!$W$15 -> 1 | K23: =Subtitling!$X$15 -> 0.5 | L23: =Subtitling!$Z$15 -> Tools | M23: =Subtitling!$AA$15 -> 0.05 | N23: =Subtitling!$AB$15 -> Note 1
A24: ='Summary (READ FIRST)'!$B$8 -> Supplier 1 | B24: ='Summary (READ FIRST)'!$B$11 -> English | C24: Subtitling | D24: Quechua | E24: EPISODIC | F24: BROADCAST/LINEAR | G24: =Subtitling!Q15 -> 26 | H24: =Subtitling!R15 -> 15 | J24: =Subtitling!$W$15 -> 1 | K24: =Subtitling!$X$15 -> 0.5 | L24: =Subtitling!$Z$15 -> Tools | M24: =Subtitling!$AA$15 -> 0.05 | N24: =Subtitling!$AB$15 -> Note 1
A25: ='Summary (READ FIRST)'!$B$8 -> Supplier 1 | B25: ='Summary (READ FIRST)'!$B$11 -> English | C25: Subtitling | D25: Quechua | E25: EPISODIC | F25: DISCOVERY/NON-SCRIPTED | G25: =Subtitling!T15 -> 38 | H25: =Subtitling!U15 -> 12 | J25: =Subtitling!$W$15 -> 1 | K25: =Subtitling!$X$15 -> 0.5 | L25: =Subtitling!$Z$15 -> Tools | M25: =Subtitling!$AA$15 -> 0.05 | N25: =Subtitling!$AB$15 -> Note 1
A26: ='Summary (READ FIRST)'!$B$8 -> Supplier 1 | B26: ='Summary (READ FIRST)'!$B$11 -> English | C26: Subtitling | D26: Quechua (Bolivia) | E26: FEATURE | F26: THEATRICAL RELEASE | G26: =Subtitling!E16 -> 23 | H26: =Subtitling!F16 -> 0 | J26: =Subtitling!$W$16 -> 1 | K26: =Subtitling!$X$16 -> 0.5 | L26: =Subtitling!$Z$16 -> Automated system | M26: =Subtitling!$AA$16 -> 0.1 | N26: =Subtitling!$AB$16 -> 0
A27: ='Summary (READ FIRST)'!$B$8 -> Supplier 1 | B27: ='Summary (READ FIRST)'!$B$11 -> English | C27: Subtitling | D27: Quechua (Bolivia) | E27: FEATURE | F27: NON-THEATRICAL - HOME ENT/STREAMING | G27: =Subtitling!H16 -> 0 | H27: =Subtitling!I16 -> 25 | J27: =Subtitling!$W$16 -> 1 | K27: =Subtitling!$X$16 -> 0.5 | L27: =Subtitling!$Z$16 -> Automated system | M27: =Subtitling!$AA$16 -> 0.1 | N27: =Subtitling!$AB$16 -> 0
A28: ='Summary (READ FIRST)'!$B$8 -> Supplier 1 | B28: ='Summary (READ FIRST)'!$B$11 -> English | C28: Subtitling | D28: Quechua (Bolivia) | E28: FEATURE | F28: NON-THEATRICAL - LINEAR BROADCAST | G28: =Subtitling!K16 -> 20 | H28: =Subtitling!L16 -> 0 | J28: =Subtitling!$W$16 -> 1 | K28: =Subtitling!$X$16 -> 0.5 | L28: =Subtitling!$Z$16 -> Automated system | M28: =Subtitling!$AA$16 -> 0.1 | N28: =Subtitling!$AB$16 -> 0
A29: ='Summary (READ FIRST)'!$B$8 -> Supplier 1 | B29: ='Summary (READ FIRST)'!$B$11 -> English | C29: Subtitling | D29: Quechua (Bolivia) | E29: EPISODIC | F29: HOME ENT/STREAMING | G29: =Subtitling!N16 -> 16 | H29: =Subtitling!O16 -> 9 | J29: =Subtitling!$W$16 -> 1 | K29: =Subtitling!$X$16 -> 0.5 | L29: =Subtitling!$Z$16 -> Automated system | M29: =Subtitling!$AA$16 -> 0.1 | N29: =Subtitling!$AB$16 -> 0
A30: ='Summary (READ FIRST)'!$B$8 -> Supplier 1 | B30: ='Summary (READ FIRST)'!$B$11 -> English | C30: Subtitling | D30: Quechua (Bolivia) | E30: EPISODIC | F30: BROADCAST/LINEAR | G30: =Subtitling!Q16 -> 12 | H30: =Subtitling!R16 -> 8 | J30: =Subtitling!$W$16 -> 1 | K30: =Subtitling!$X$16 -> 0.5 | L30: =Subtitling!$Z$16 -> Automated system | M30: =Subtitling!$AA$16 -> 0.1 | N30: =Subtitling!$AB$16 -> 0
A31: ='Summary (READ FIRST)'!$B$8 -> Supplier 1 | B31: ='Summary (READ FIRST)'!$B$11 -> English | C31: Subtitling | D31: Quechua (Bolivia) | E31: EPISODIC | F31: DISCOVERY/NON-SCRIPTED | G31: =Subtitling!T16 -> 33 | H31: =Subtitling!U16 -> 21 | J31: =Subtitling!$W$16 -> 1 | K31: =Subtitling!$X$16 -> 0.5 | L31: =Subtitling!$Z$16 -> Automated system | M31: =Subtitling!$AA$16 -> 0.1 | N31: =Subtitling!$AB$16 -> 0
A32: ='Summary (READ FIRST)'!$B$8 -> Supplier 1 | B32: ='Summary (READ FIRST)'!$B$11 -> English | C32: Subtitling | D32: Quechua (Ecuador) | E32: FEATURE | F32: THEATRICAL RELEASE | G32: =Subtitling!E17 -> 40 | H32: =Subtitling!F17 -> 20 | J32: =Subtitling!$W$17 -> 1 | K32: =Subtitling!$X$17 -> 0.5 | L32: =Subtitling!$Z$17 -> Workflow | M32: =Subtitling!$AA$17 -> 0.1 | N32: =Subtitling!$AB$17 -> Note 1
A33: ='Summary (READ FIRST)'!$B$8 -> Supplier 1 | B33: ='Summary (READ FIRST)'!$B$11 -> English | C33: Subtitling | D33: Quechua (Ecuador) | E33: FEATURE | F33: NON-THEATRICAL - HOME ENT/STREAMING | G33: =Subtitling!H17 -> 20 | H33: =Subtitling!I17 -> 17 | J33: =Subtitling!$W$17 -> 1 | K33: =Subtitling!$X$17 -> 0.5 | L33: =Subtitling!$Z$17 -> Workflow | M33: =Subtitling!$AA$17 -> 0.1 | N33: =Subtitling!$AB$17 -> Note 1
A34: ='Summary (READ FIRST)'!$B$8 -> Supplier 1 | B34: ='Summary (READ FIRST)'!$B$11 -> English | C34: Subtitling | D34: Quechua (Ecuador) | E34: FEATURE | F34: NON-THEATRICAL - LINEAR BROADCAST | G34: =Subtitling!K17 -> 34 | H34: =Subtitling!L17 -> 18 | J34: =Subtitling!$W$17 -> 1 | K34: =Subtitling!$X$17 -> 0.5 | L34: =Subtitling!$Z$17 -> Workflow | M34: =Subtitling!$AA$17 -> 0.1 | N34: =Subtitling!$AB$17 -> Note 1
A35: ='Summary (READ FIRST)'!$B$8 -> Supplier 1 | B35: ='Summary (READ FIRST)'!$B$11 -> English | C35: Subtitling | D35: Quechua (Ecuador) | E35: EPISODIC | F35: HOME ENT/STREAMING | G35: =Subtitling!N17 -> 34 | H35: =Subtitling!O17 -> 0 | J35: =Subtitling!$W$17 -> 1 | K35: =Subtitling!$X$17 -> 0.5 | L35: =Subtitling!$Z$17 -> Workflow | M35: =Subtitling!$AA$17 -> 0.1 | N35: =Subtitling!$AB$17 -> Note 1
A36: ='Summary (READ FIRST)'!$B$8 -> Supplier 1 | B36: ='Summary (READ FIRST)'!$B$11 -> English | C36: Subtitling | D36: Quechua (Ecuador) | E36: EPISODIC | F36: BROADCAST/LINEAR | G36: =Subtitling!Q17 -> 0 | H36: =Subtitling!R17 -> 0 | J36: =Subtitling!$W$17 -> 1 | K36: =Subtitling!$X$17 -> 0.5 | L36: =Subtitling!$Z$17 -> Workflow | M36: =Subtitling!$AA$17 -> 0.1 | N36: =Subtitling!$AB$17 -> Note 1
A37: ='Summary (READ FIRST)'!$B$8 -> Supplier 1 | B37: ='Summary (READ FIRST)'!$B$11 -> English | C37: Subtitling | D37: Quechua (Ecuador) | E37: EPISODIC | F37: DISCOVERY/NON-SCRIPTED | G37: =Subtitling!T17 -> 0 | H37: =Subtitling!U17 -> 0 | J37: =Subtitling!$W$17 -> 1 | K37: =Subtitling!$X$17 -> 0.5 | L37: =Subtitling!$Z$17 -> Workflow | M37: =Subtitling!$AA$17 -> 0.1 | N37: =Subtitling!$AB$17 -> Note 1
A38: ='Summary (READ FIRST)'!$B$8 -> Supplier 1 | B38: ='Summary (READ FIRST)'!$B$11 -> English | C38: Subtitling | D38: Quechua (Peru) | E38: FEATURE | F38: THEATRICAL RELEASE | G38: =Subtitling!E18 -> 29 | H38: =Subtitling!F18 -> 25 | J38: =Subtitling!$W$18 -> 0 | K38: =Subtitling!$X$18 -> 0 | L38: =Subtitling!$Z$18 -> 0 | M38: =Subtitling!$AA$18 -> 0 | N38: =Subtitling!$AB$18 -> Note 1
A39: ='Summary (READ FIRST)'!$B$8 -> Supplier 1 | B39: ='Summary (READ FIRST)'!$B$11 -> English | C39: Subtitling | D39: Quechua (Peru) | E39: FEATURE | F39: NON-THEATRICAL - HOME ENT/STREAMING | G39: =Subtitling!H18 -> 37 | H39: =Subtitling!I18 -> 24 | J39: =Subtitling!$W$18 -> 0 | K39: =Subtitling!$X$18 -> 0 | L39: =Subtitling!$Z$18 -> 0 | M39: =Subtitling!$AA$18 -> 0 | N39: =Subtitling!$AB$18 -> Note 1
A40: ='Summary (READ FIRST)'!$B$8 -> Supplier 1 | B40: ='Summary (READ FIRST)'!$B$11 -> English | C40: Subtitling | D40: Quechua (Peru) | E40: FEATURE | F40: NON-THEATRICAL - LINEAR BROADCAST | G40: =Subtitling!K18 -> 25 | H40: =Subtitling!L18 -> 0 | J40: =Subtitling!$W$18 -> 0 | K40: =Subtitling!$X$18 -> 0 | L40: =Subtitling!$Z$18 -> 0 | M40: =Subtitling!$AA$18 -> 0 | N40: =Subtitling!$AB$18 -> Note 1
A41: ='Summary (READ FIRST)'!$B$8 -> Supplier 1 | B41: ='Summary (READ FIRST)'!$B$11 -> English | C41: Subtitling | D41: Quechua (Peru) | E41: EPISODIC | F41: HOME ENT/STREAMING | G41: =Subtitling!N18 -> 16 | H41: =Subtitling!O18 -> 13 | J41: =Subtitling!$W$18 -> 0 | K41: =Subtitling!$X$18 -> 0 | L41: =Subtitling!$Z$18 -> 0 | M41: =Subtitling!$AA$18 -> 0 | N41: =Subtitling!$AB$18 -> Note 1
A42: ='Summary (READ FIRST)'!$B$8 -> Supplier 1 | B42: ='Summary (READ FIRST)'!$B$11 -> English | C42: Subtitling | D42: Quechua (Peru) | E42: EPISODIC | F42: BROADCAST/LINEAR | G42: =Subtitling!Q18 -> 40 | H42: =Subtitling!R18 -> 25 | J42: =Subtitling!$W$18 -> 0 | K42: =Subtitling!$X$18 -> 0 | L42: =Subtitling!$Z$18 -> 0 | M42: =Subtitling!$AA$18 -> 0 | N42: =Subtitling!$AB$18 -> Note 1
A43: ='Summary (READ FIRST)'!$B$8 -> Supplier 1 | B43: ='Summary (READ FIRST)'!$B$11 -> English | C43: Subtitling | D43: Quechua (Peru) | E43: EPISODIC | F43: DISCOVERY/NON-SCRIPTED | G43: =Subtitling!T18 -> 27 | H43: =Subtitling!U18 -> 12 | J43: =Subtitling!$W$18 -> 0 | K43: =Subtitling!$X$18 -> 0 | L43: =Subtitling!$Z$18 -> 0 | M43: =Subtitling!$AA$18 -> 0 | N43: =Subtitling!$AB$18 -> Note 1
A44: ='Summary (READ FIRST)'!$B$8 -> Supplier 1 | B44: ='Summary (READ FIRST)'!$B$11 -> English | C44: Subtitling | D44: Spanish (Colombia) | E44: FEATURE | F44: THEATRICAL RELEASE | G44: =Subtitling!E19 -> 0 | H44: =Subtitling!F19 -> 22 | J44: =Subtitling!$W$19 -> 1 | K44: =Subtitling!$X$19 -> 0.5 | L44: =Subtitling!$Z$19 -> Automated system | M44: =Subtitling!$AA$19 -> 0.2 | N44: =Subtitling!$AB$19 -> Note 1
A45: ='Summary (READ FIRST)'!$B$8 -> Supplier 1 | B45: ='Summary (READ FIRST)'!$B$11 -> English | C45: Subtitling | D45: Spanish (Colombia) | E45: FEATURE | F45: NON-THEATRICAL - HOME ENT/STREAMING | G45: =Subtitling!H19 -> 0 | H45: =Subtitling!I19 -> 15 | J45: =Subtitling!$W$19 -> 1 | K45: =Subtitling!$X$19 -> 0.5 | L45: =Subtitling!$Z$19 -> Automated system | M45: =Subtitling!$AA$19 -> 0.2 | N45: =Subtitling!$AB$19 -> Note 1
A46: ='Summary (READ FIRST)'!$B$8 -> Supplier 1 | B46: ='Summary (READ FIRST)'!$B$11 -> English | C46: Subtitling | D46: Spanish (Colombia) | E46: FEATURE | F46: NON-THEATRICAL - LINEAR BROADCAST | G46: =Subtitling!K19 -> 35 | H46: =Subtitling!L19 -> 8 | J46: =Subtitling!$W$19 -> 1 | K46: =Subtitling!$X$19 -> 0.5 | L46: =Subtitling!$Z$19 -> Automated system | M46: =Subtitling!$AA$19 -> 0.2 | N46: =Subtitling!$AB$19 -> Note 1
A47: ='Summary (READ FIRST)'!$B$8 -> Supplier 1 | B47: ='Summary (READ FIRST)'!$B$11 -> English | C47: Subtitling | D47: Spanish (Colombia) | E47: EPISODIC | F47: HOME ENT/STREAMING | G47: =Subtitling!N19 -> 0 | H47: =Subtitling!O19 -> 8 | J47: =Subtitling!$W$19 -> 1 | K47: =Subtitling!$X$19 -> 0.5 | L47: =Subtitling!$Z$19 -> Automated system | M47: =Subtitling!$AA$19 -> 0.2 | N47: =Subtitling!$AB$19 -> Note 1
A48: ='Summary (READ FIRST)'!$B$8 -> Supplier 1 | B48: ='Summary (READ FIRST)'!$B$11 -> English | C48: Subtitling | D48: Spanish (Colombia) | E48: EPISODIC | F48: BROADCAST/LINEAR | G48: =Subtitling!Q19 -> 21 | H48: =Subtitling!R19 -> 14 | J48: =Subtitling!$W$19 -> 1 | K48: =Subtitling!$X$19 -> 0.5 | L48: =Subtitling!$Z$19 -> Automated system | M48: =Subtitling!$AA$19 -> 0.2 | N48: =Subtitling!$AB$19 -> Note 1
A49: ='Summary (READ FIRST)'!$B$8 -> Supplier 1 | B49: ='Summary (READ FIRST)'!$B$11 -> English | C49: Subtitling | D49: Spanish (Colombia) | E49: EPISODIC | F49: DISCOVERY/NON-SCRIPTED | G49: =Subtitling!T19 -> 23 | H49: =Subtitling!U19 -> 14 | J49: =Subtitling!$W$19 -> 1 | K49: =Subtitling!$X$19 -> 0.5 | L49: =Subtitling!$Z$19 -> Automated system | M49: =Subtitling!$AA$19 -> 0.2 | N49: =Subtitling!$AB$19 -> Note 1
A50: ='Summary (READ FIRST)'!$B$8 -> Supplier 1 | B50: ='Summary (READ FIRST)'!$B$11 -> English | C50: Subtitling | D50: Spanish (Mexico) | E50: FEATURE | F50: THEATRICAL RELEASE | G50: =Subtitling!E20 -> 31 | H50: =Subtitling!F20 -> 0 | J50: =Subtitling!$W$20 -> 1 | K50: =Subtitling!$X$20 -> 0.5 | L50: =Subtitling!$Z$20 -> Tools | M50: =Subtitling!$AA$20 -> 0.05 | N50: =Subtitling!$AB$20 -> 0
A51: ='Summary (READ FIRST)'!$B$8 -> Supplier 1 | B51: ='Summary (READ FIRST)'!$B$11 -> English | C51: Subtitling | D51: Spanish (Mexico) | E51: FEATURE | F51: NON-THEATRICAL - HOME ENT/STREAMING | G51: =Subtitling!H20 -> 39 | H51: =Subtitling!I20 -> 0 | J51: =Subtitling!$W$20 -> 1 | K51: =Subtitling!$X$20 -> 0.5 | L51: =Subtitling!$Z$20 -> Tools | M51: =Subtitling!$AA$20 -> 0.05 | N51: =Subtitling!$AB$20 -> 0
A52: ='Summary (READ FIRST)'!$B$8 -> Supplier 1 | B52: ='Summary (READ FIRST)'!$B$11 -> English | C52: Subtitling | D52: Spanish (Mexico) | E52: FEATURE | F52: NON-THEATRICAL - LINEAR BROADCAST | G52: =Subtitling!K20 -> 0 | H52: =Subtitling!L20 -> 0 | J52: =Subtitling!$W$20 -> 1 | K52: =Subtitling!$X$20 -> 0.5 | L52: =Subtitling!$Z$20 -> Tools | M52: =Subtitling!$AA$20 -> 0.05 | N52: =Subtitling!$AB$20 -> 0
A53: ='Summary (READ FIRST)'!$B$8 -> Supplier 1 | B53: ='Summary (READ FIRST)'!$B$11 -> English | C53: Subtitling | D53: Spanish (Mexico) | E53: EPISODIC | F53: HOME ENT/STREAMING | G53: =Subtitling!N20 -> 22 | H53: =Subtitling!O20 -> 15 | J53: =Subtitling!$W$20 -> 1 | K53: =Subtitling!$X$20 -> 0.5 | L53: =Subtitling!$Z$20 -> Tools | M53: =Subtitling!$AA$20 -> 0.05 | N53: =Subtitling!$AB$20 -> 0
A54: ='Summary (READ FIRST)'!$B$8 -> Supplier 1 | B54: ='Summary (READ FIRST)'!$B$11 -> English | C54: Subtitling | D54: Spanish (Mexico) | E54: EPISODIC | F54: BROADCAST/LINEAR | G54: =Subtitling!Q20 -> 33 | H54: =Subtitling!R20 -> 21 | J54: =Subtitling!$W$20 -> 1 | K54: =Subtitling!$X$20 -> 0.5 | L54: =Subtitling!$Z$20 -> Tools | M54: =Subtitling!$AA$20 -> 0.05 | N54: =Subtitling!$AB$20 -> 0
A55: ='Summary (READ FIRST)'!$B$8 -> Supplier 1 | B55: ='Summary (READ FIRST)'!$B$11 -> English | C55: Subtitling | D55: Spanish (Mexico) | E55: EPISODIC | F55: DISCOVERY/NON-SCRIPTED | G55: =Subtitling!T20 -> 0 | H55: =Subtitling!U20 -> 21 | J55: =Subtitling!$W$20 -> 1 | K55: =Subtitling!$X$20 -> 0.5 | L55: =Subtitling!$Z$20 -> Tools | M55: =Subtitling!$AA$20 -> 0.05 | N55: =Subtitling!$AB$20 -> 0
A56: ='Summary (READ FIRST)'!$B$8 -> Supplier 1 | B56: ='Summary (READ FIRST)'!$B$11 -> English | C56: Subtitling | D56: Spanish (Latin American) | E56: FEATURE | F56: THEATRICAL RELEASE | G56: =Subtitling!E21 -> 37 | H56: =Subtitling!F21 -> 23 | J56: =Subtitling!$W$21 -> 1 | K56: =Subtitling!$X$21 -> 0.5 | L56: =Subtitling!$Z$21 -> Workflow | M56: =Subtitling!$AA$21 -> 0.15 | N56: =Subtitling!$AB$21 -> Note 1
A57: ='Summary (READ FIRST)'!$B$8 -> Supplier 1 | B57: ='Summary (READ FIRST)'!$B$11 -> English | C57: Subtitling | D57: Spanish (Latin American) | E57: FEATURE | F57: NON-THEATRICAL - HOME ENT/STREAMING | G57: =Subtitling!H21 -> 27 | H57: =Subtitling!I21 -> 19 | J57: =Subtitling!$W$21 -> 1 | K57: =Subtitling!$X$21 -> 0.5 | L57: =Subtitling!$Z$21 -> Workflow | M57: =Subtitling!$AA$21 -> 0.15 | N57: =Subtitling!$AB$21 -> Note 1
A58: ='Summary (READ FIRST)'!$B$8 -> Supplier 1 | B58: ='Summary (READ FIRST)'!$B$11 -> English | C58: Subtitling | D58: Spanish (Latin American) | E58: FEATURE | F58: NON-THEATRICAL - LINEAR BROADCAST | G58: =Subtitling!K21 -> 22 | H58: =Subtitling!L21 -> 14 | J58: =Subtitling!$W$21 -> 1 | K58: =Subtitling!$X$21 -> 0.5 | L58: =Subtitling!$Z$21 -> Workflow | M58: =Subtitling!$AA$21 -> 0.15 | N58: =Subtitling!$AB$21 -> Note 1
A59: ='Summary (READ FIRST)'!$B$8 -> Supplier 1 | B59: ='Summary (READ FIRST)'!$B$11 -> English | C59: Subtitling | D59: Spanish (Latin American) | E59: EPISODIC | F59: HOME ENT/STREAMING | G59: =Subtitling!N21 -> 22 | H59: =Subtitling!O21 -> 0 | J59: =Subtitling!$W$21 -> 1 | K59: =Subtitling!$X$21 -> 0.5 | L59: =Subtitling!$Z$21 -> Workflow | M59: =Subtitling!$AA$21 -> 0.15 | N59: =Subtitling!$AB$21 -> Note 1
A60: ='Summary (READ FIRST)'!$B$8 -> Supplier 1 | B60: ='Summary (READ FIRST)'!$B$11 -> English | C60: Subtitling | D60: Spanish (Latin American) | E60: EPISODIC | F60: BROADCAST/LINEAR | G60: =Subtitling!Q21 -> 29 | H60: =Subtitling!R21 -> 0 | J60: =Subtitling!$W$21 -> 1 | K60: =Subtitling!$X$21 -> 0.5 | L60: =Subtitling!$Z$21 -> Workflow | M60: =Subtitling!$AA$21 -> 0.15 | N60: =Subtitling!$AB$21 -> Note 1
A61: ='Summary (READ FIRST)'!$B$8 -> Supplier 1 | B61: ='Summary (READ FIRST)'!$B$11 -> English | C61: Subtitling | D61: Spanish (Latin American) | E61: EPISODIC | F61: DISCOVERY/NON-SCRIPTED | G61: =Subtitling!T21 -> 26 | H61: =Subtitling!U21 -> 0 | J61: =Subtitling!$W$21 -> 1 | K61: =Subtitling!$X$21 -> 0.5 | L61: =Subtitling!$Z$21 -> Workflow | M61: =Subtitling!$AA$21 -> 0.15 | N61: =Subtitling!$AB$21 -> Note 1
A62: ='Summary (READ FIRST)'!$B$8 -> Supplier 1 | B62: ='Summary (READ FIRST)'!$B$11 -> English | C62: Subtitling | D62: Zapotec | E62: FEATURE | F62: THEATRICAL RELEASE | G62: =Subtitling!E22 -> 26 | H62: =Subtitling!F22 -> 18 | J62: =Subtitling!$W$22 -> 1 | K62: =Subtitling!$X$22 -> 0.5 | L62: =Subtitling!$Z$22 -> Tools | M62: =Subtitling!$AA$22 -> 0.1 | N62: =Subtitling!$AB$22 -> Note 1
A63: ='Summary (READ FIRST)'!$B$8 -> Supplier 1 | B63: ='Summary (READ FIRST)'!$B$11 -> English | C63: Subtitling | D63: Zapotec | E63: FEATURE | F63: NON-THEATRICAL - HOME ENT/STREAMING | G63: =Subtitling!H22 -> 23 | H63: =Subtitling!I22 -> 17 | J63: =Subtitling!$W$22 -> 1 | K63: =Subtitling!$X$22 -> 0.5 | L63: =Subtitling!$Z$22 -> Tools | M63: =Subtitling!$AA$22 -> 0.1 | N63: =Subtitling!$AB$22 -> Note 1
A64: ='Summary (READ FIRST)'!$B$8 -> Supplier 1 | B64: ='Summary (READ FIRST)'!$B$11 -> English | C64: Subtitling | D64: Zapotec | E64: FEATURE | F64: NON-THEATRICAL - LINEAR BROADCAST | G64: =Subtitling!K22 -> 39 | H64: =Subtitling!L22 -> 19 | J64: =Subtitling!$W$22 -> 1 | K64: =Subtitling!$X$22 -> 0.5 | L64: =Subtitling!$Z$22 -> Tools | M64: =Subtitling!$AA$22 -> 0.1 | N64: =Subtitling!$AB$22 -> Note 1
A65: ='Summary (READ FIRST)'!$B$8 -> Supplier 1 | B65: ='Summary (READ FIRST)'!$B$11 -> English | C65: Subtitling | D65: Zapotec | E65: EPISODIC | F65: HOME ENT/STREAMING | G65: =Subtitling!N22 -> 35 | H65: =Subtitling!O22 -> 22 | J65: =Subtitling!$W$22 -> 1 | K65: =Subtitling!$X$22 -> 0.5 | L65: =Subtitling!$Z$22 -> Tools | M65: =Subtitling!$AA$22 -> 0.1 | N65: =Subtitling!$AB$22 -> Note 1
A66: ='Summary (READ FIRST)'!$B$8 -> Supplier 1 | B66: ='Summary (READ FIRST)'!$B$11 -> English | C66: Subtitling | D66: Zapotec | E66: EPISODIC | F66: BROADCAST/LINEAR | G66: =Subtitling!Q22 -> 0 | H66: =Subtitling!R22 -> 26 | J66: =Subtitling!$W$22 -> 1 | K66: =Subtitling!$X$22 -> 0.5 | L66: =Subtitling!$Z$22 -> Tools | M66: =Subtitling!$AA$22 -> 0.1 | N66: =Subtitling!$AB$22 -> Note 1
A67: ='Summary (READ FIRST)'!$B$8 -> Supplier 1 | B67: ='Summary (READ FIRST)'!$B$11 -> English | C67: Subtitling | D67: Zapotec | E67: EPISODIC | F67: DISCOVERY/NON-SCRIPTED | G67: =Subtitling!T22 -> 20 | H67: =Subtitling!U22 -> 13 | J67: =Subtitling!$W$22 -> 1 | K67: =Subtitling!$X$22 -> 0.5 | L67: =Subtitling!$Z$22 -> Tools | M67: =Subtitling!$AA$22 -> 0.1 | N67: =Subtitling!$AB$22 -> Note 1
A68: ='Summary (READ FIRST)'!$B$8 -> Supplier 1 | B68: ='Summary (READ FIRST)'!$B$11 -> English | C68: CC & HOH | D68: Aymara | E68: FEATURE | F68: THEATRICAL RELEASE | G68: ='CC & HOH'!E12 -> 15 | H68: ='CC & HOH'!F12 -> 7 | J68: ='CC & HOH'!$W$12 -> 1 | K68: ='CC & HOH'!$X$12 -> 0.5 | L68: ='CC & HOH'!$Z$12 -> Tools | M68: ='CC & HOH'!$AA$12 -> 0.15 | N68: ='CC & HOH'!$AB$12 -> Note 2
A69: ='Summary (READ FIRST)'!$B$8 -> Supplier 1 | B69: ='Summary (READ FIRST)'!$B$11 -> English | C69: CC & HOH | D69: Aymara | E69: FEATURE | F69: NON-THEATRICAL - HOME ENT/STREAMING | G69: ='CC & HOH'!H12 -> 5 | H69: ='CC & HOH'!I12 -> 4 | J69: ='CC & HOH'!$W$12 -> 1 | K69: ='CC & HOH'!$X$12 -> 0.5 | L69: ='CC & HOH'!$Z$12 -> Tools | M69: ='CC & HOH'!$AA$12 -> 0.15 | N69: ='CC & HOH'!$AB$12 -> Note 2
A70: ='Summary (READ FIRST)'!$B$8 -> Supplier 1 | B70: ='Summary (READ FIRST)'!$B$11 -> English | C70: CC & HOH | D70: Aymara | E70: FEATURE | F70: NON-THEATRICAL - LINEAR BROADCAST | G70: ='CC & HOH'!K12 -> 10 | H70: ='CC & HOH'!L12 -> 9 | J70: ='CC & HOH'!$W$12 -> 1 | K70: ='CC & HOH'!$X$12 -> 0.5 | L70: ='CC & HOH'!$Z$12 -> Tools | M70: ='CC & HOH'!$AA$12 -> 0.15 | N70: ='CC & HOH'!$AB$12 -> Note 2
A71: ='Summary (READ FIRST)'!$B$8 -> Supplier 1 | B71: ='Summary (READ FIRST)'!$B$11 -> English | C71: CC & HOH | D71: Aymara | E71: EPISODIC | F71: HOME ENT/STREAMING | G71: ='CC & HOH'!N12 -> 8 | H71: ='CC & HOH'!O12 -> 3 | J71: ='CC & HOH'!$W$12 -> 1 | K71: ='CC & HOH'!$X$12 -> 0.5 | L71: ='CC & HOH'!$Z$12 -> Tools | M71: ='CC & HOH'!$AA$12 -> 0.15 | N71: ='CC & HOH'!$AB$12 -> Note 2
A72: ='Summary (READ FIRST)'!$B$8 -> Supplier 1 | B72: ='Summary (READ FIRST)'!$B$11 -> English | C72: CC & HOH | D72: Aymara | E72: EPISODIC | F72: BROADCAST/LINEAR | G72: ='CC & HOH'!Q12 -> 0 | H72: ='CC & HOH'!R12 -> 8 | J72: ='CC & HOH'!$W$12 -> 1 | K72: ='CC & HOH'!$X$12 -> 0.5 | L72: ='CC & HOH'!$Z$12 -> Tools | M72: ='CC & HOH'!$AA$12 -> 0.15 | N72: ='CC & HOH'!$AB$12 -> Note 2
A73: ='Summary (READ FIRST)'!$B$8 -> Supplier 1 | B73: ='Summary (READ FIRST)'!$B$11 -> English | C73: CC & HOH | D73: Aymara | E73: EPISODIC | F73: DISCOVERY/NON-SCRIPTED | G73: ='CC & HOH'!T12 -> 12 | H73: ='CC & HOH'!U12 -> 8 | J73: ='CC & HOH'!$W$12 -> 1 | K73: ='CC & HOH'!$X$12 -> 0.5 | L73: ='CC & HOH'!$Z$12 -> Tools | M73: ='CC & HOH'!$AA$12 -> 0.15 | N73: ='CC & HOH'!$AB$12 -> Note 2
A74: ='Summary (READ FIRST)'!$B$8 -> Supplier 1 | B74: ='Summary (READ FIRST)'!$B$11 -> English | C74: CC & HOH | D74: Mayan | E74: FEATURE | F74: THEATRICAL RELEASE | G74: ='CC & HOH'!E13 -> 17 | H74: ='CC & HOH'!F13 -> 0 | J74: ='CC & HOH'!$W$13 -> 0 | K74: ='CC & HOH'!$X$13 -> 0.5 | L74: ='CC & HOH'!$Z$13 -> Workflow | M74: ='CC & HOH'!$AA$13 -> 0.1 | N74: ='CC & HOH'!$AB$13 -> Note 2
A75: ='Summary (READ FIRST)'!$B$8 -> Supplier 1 | B75: ='Summary (READ FIRST)'!$B$11 -> English | C75: CC & HOH | D75: Mayan | E75: FEATURE | F75: NON-THEATRICAL - HOME ENT/STREAMING | G75: ='CC & HOH'!H13 -> 6 | H75: ='CC & HOH'!I13 -> 0 | J75: ='CC & HOH'!$W$13 -> 0 | K75: ='CC & HOH'!$X$13 -> 0.5 | L75: ='CC & HOH'!$Z$13 -> Workflow | M75: ='CC & HOH'!$AA$13 -> 0.1 | N75: ='CC & HOH'!$AB$13 -> Note 2
A76: ='Summary (READ FIRST)'!$B$8 -> Supplier 1 | B76: ='Summary (READ FIRST)'!$B$11 -> English | C76: CC & HOH | D76: Mayan | E76: FEATURE | F76: NON-THEATRICAL - LINEAR BROADCAST | G76: ='CC & HOH'!K13 -> 11 | H76: ='CC & HOH'!L13 -> 0 | J76: ='CC & HOH'!$W$13 -> 0 | K76: ='CC & HOH'!$X$13 -> 0.5 | L76: ='CC & HOH'!$Z$13 -> Workflow | M76: ='CC & HOH'!$AA$13 -> 0.1 | N76: ='CC & HOH'!$AB$13 -> Note 2
A77: ='Summary (READ FIRST)'!$B$8 -> Supplier 1 | B77: ='Summary (READ FIRST)'!$B$11 -> English | C77: CC & HOH | D77: Mayan | E77: EPISODIC | F77: HOME ENT/STREAMING | G77: ='CC & HOH'!N13 -> 10 | H77: ='CC & HOH'!O13 -> 6 | J77: ='CC & HOH'!$W$13 -> 0 | K77: ='CC & HOH'!$X$13 -> 0.5 | L77: ='CC & HOH'!$Z$13 -> Workflow | M77: ='CC & HOH'!$AA$13 -> 0.1 | N77: ='CC & HOH'!$AB$13 -> Note 2
A78: ='Summary (READ FIRST)'!$B$8 -> Supplier 1 | B78: ='Summary (READ FIRST)'!$B$11 -> English | C78: CC & HOH | D78: Mayan | E78: EPISODIC | F78: BROADCAST/LINEAR | G78: ='CC & HOH'!Q13 -> 12 | H78: ='CC & HOH'!R13 -> 9 | J78: ='CC & HOH'!$W$13 -> 0 | K78: ='CC & HOH'!$X$13 -> 0.5 | L78: ='CC & HOH'!$Z$13 -> Workflow | M78: ='CC & HOH'!$AA$13 -> 0.1 | N78: ='CC & HOH'!$AB$13 -> Note 2
A79: ='Summary (READ FIRST)'!$B$8 -> Supplier 1 | B79: ='Summary (READ FIRST)'!$B$11 -> English | C79: CC & HOH | D79: Mayan | E79: EPISODIC | F79: DISCOVERY/NON-SCRIPTED | G79: ='CC & HOH'!T13 -> 8 | H79: ='CC & HOH'!U13 -> 4 | J79: ='CC & HOH'!$W$13 -> 0 | K79: ='CC & HOH'!$X$13 -> 0.5 | L79: ='CC & HOH'!$Z$13 -> Workflow | M79: ='CC & HOH'!$AA$13 -> 0.1 | N79: ='CC & HOH'!$AB$13 -> Note 2
A80: ='Summary (READ FIRST)'!$B$8 -> Supplier 1 | B80: ='Summary (READ FIRST)'!$B$11 -> English | C80: CC & HOH | D80: Portuguese (Brazil) | E80: FEATURE | F80: THEATRICAL RELEASE | G80: ='CC & HOH'!E14 -> 8 | H80: ='CC & HOH'!F14 -> 3 | J80: ='CC & HOH'!$W$14 -> 1 | K80: ='CC & HOH'!$X$14 -> 0.5 | L80: ='CC & HOH'!$Z$14 -> 0 | M80: ='CC & HOH'!$AA$14 -> 0.05 | N80: ='CC & HOH'!$AB$14 -> Note 2
A81: ='Summary (READ FIRST)'!$B$8 -> Supplier 1 | B81: ='Summary (READ FIRST)'!$B$11 -> English | C81: CC & HOH | D81: Portuguese (Brazil) | E81: FEATURE | F81: NON-THEATRICAL - HOME ENT/STREAMING | G81: ='CC & HOH'!H14 -> 10 | H81: ='CC & HOH'!I14 -> 4 | J81: ='CC & HOH'!$W$14 -> 1 | K81: ='CC & HOH'!$X$14 -> 0.5 | L81: ='CC & HOH'!$Z$14 -> 0 | M81: ='CC & HOH'!$AA$14 -> 0.05 | N81: ='CC & HOH'!$AB$14 -> Note 2
A82: ='Summary (READ FIRST)'!$B$8 -> Supplier 1 | B82: ='Summary (READ FIRST)'!$B$11 -> English | C82: CC & HOH | D82: Portuguese (Brazil) | E82: FEATURE | F82: NON-THEATRICAL - LINEAR BROADCAST | G82: ='CC & HOH'!K14 -> 0 | H82: ='CC & HOH'!L14 -> 6 | J82: ='CC & HOH'!$W$14 -> 1 | K82: ='CC & HOH'!$X$14 -> 0.5 | L82: ='CC & HOH'!$Z$14 -> 0 | M82: ='CC & HOH'!$AA$14 -> 0.05 | N82: ='CC & HOH'!$AB$14 -> Note 2
A83: ='Summary (READ FIRST)'!$B$8 -> Supplier 1 | B83: ='Summary (READ FIRST)'!$B$11 -> English | C83: CC & HOH | D83: Portuguese (Brazil) | E83: EPISODIC | F83: HOME ENT/STREAMING | G83: ='CC & HOH'!N14 -> 13 | H83: ='CC & HOH'!O14 -> 10 | J83: ='CC & HOH'!$W$14 -> 1 | K83: ='CC & HOH'!$X$14 -> 0.5 | L83: ='CC & HOH'!$Z$14 -> 0 | M83: ='CC & HOH'!$AA$14 -> 0.05 | N83: ='CC & HOH'!$AB$14 -> Note 2
A84: ='Summary (READ FIRST)'!$B$8 -> Supplier 1 | B84: ='Summary (READ FIRST)'!$B$11 -> English | C84: CC & HOH | D84: Portuguese (Brazil) | E84: EPISODIC | F84: BROADCAST/LINEAR | G84: ='CC & HOH'!Q14 -> 7 | H84: ='CC & HOH'!R14 -> 0 | J84: ='CC & HOH'!$W$14 -> 1 | K84: ='CC & HOH'!$X$14 -> 0.5 | L84: ='CC & HOH'!$Z$14 -> 0 | M84: ='CC & HOH'!$AA$14 -> 0.05 | N84: ='CC & HOH'!$AB$14 -> Note 2
A85: ='Summary (READ FIRST)'!$B$8 -> Supplier 1 | B85: ='Summary (READ FIRST)'!$B$11 -> English | C85: CC & HOH | D85: Portuguese (Brazil) | E85: EPISODIC | F85: DISCOVERY/NON-SCRIPTED | G85: ='CC & HOH'!T14 -> 0 | H85: ='CC & HOH'!U14 -> 8 | J85: ='CC & HOH'!$W$14 -> 1 | K85: ='CC & HOH'!$X$14 -> 0.5 | L85: ='CC & HOH'!$Z$14 -> 0 | M85: ='CC & HOH'!$AA$14 -> 0.05 | N85: ='CC & HOH'!$AB$14 -> Note 2
A86: ='Summary (READ FIRST)'!$B$8 -> Supplier 1 | B86: ='Summary (READ FIRST)'!$B$11 -> English | C86: CC & HOH | D86: Quechua | E86: FEATURE | F86: THEATRICAL RELEASE | G86: ='CC & HOH'!E15 -> 15 | H86: ='CC & HOH'!F15 -> 10 | J86: ='CC & HOH'!$W$15 -> 1 | K86: ='CC & HOH'!$X$15 -> 0.5 | L86: ='CC & HOH'!$Z$15 -> Tools | M86: ='CC & HOH'!$AA$15 -> 0 | N86: ='CC & HOH'!$AB$15 -> 0
A87: ='Summary (READ FIRST)'!$B$8 -> Supplier 1 | B87: ='Summary (READ FIRST)'!$B$11 -> English | C87: CC & HOH | D87: Quechua | E87: FEATURE | F87: NON-THEATRICAL - HOME ENT/STREAMING | G87: ='CC & HOH'!H15 -> 9 | H87: ='CC & HOH'!I15 -> 7 | J87: ='CC & HOH'!$W$15 -> 1 | K87: ='CC & HOH'!$X$15 -> 0.5 | L87: ='CC & HOH'!$Z$15 -> Tools | M87: ='CC & HOH'!$AA$15 -> 0 | N87: ='CC & HOH'!$AB$15 -> 0
A88: ='Summary (READ FIRST)'!$B$8 -> Supplier 1 | B88: ='Summary (READ FIRST)'!$B$11 -> English | C88: CC & HOH | D88: Quechua | E88: FEATURE | F88: NON-THEATRICAL - LINEAR BROADCAST | G88: ='CC & HOH'!K15 -> 8 | H88: ='CC & HOH'!L15 -> 7 | J88: ='CC & HOH'!$W$15 -> 1 | K88: ='CC & HOH'!$X$15 -> 0.5 | L88: ='CC & HOH'!$Z$15 -> Tools | M88: ='CC & HOH'!$AA$15 -> 0 | N88: ='CC & HOH'!$AB$15 -> 0
A89: ='Summary (READ FIRST)'!$B$8 -> Supplier 1 | B89: ='Summary (READ FIRST)'!$B$11 -> English | C89: CC & HOH | D89: Quechua | E89: EPISODIC | F89: HOME ENT/STREAMING | G89: ='CC & HOH'!N15 -> 0 | H89: ='CC & HOH'!O15 -> 8 | J89: ='CC & HOH'!$W$15 -> 1 | K89: ='CC & HOH'!$X$15 -> 0.5 | L89: ='CC & HOH'!$Z$15 -> Tools | M89: ='CC & HOH'!$AA$15 -> 0 | N89: ='CC & HOH'!$AB$15 -> 0
A90: ='Summary (READ FIRST)'!$B$8 -> Supplier 1 | B90: ='Summary (READ FIRST)'!$B$11 -> English | C90: CC & HOH | D90: Quechua | E90: EPISODIC | F90: BROADCAST/LINEAR | G90: ='CC & HOH'!Q15 -> 9 | H90: ='CC & HOH'!R15 -> 5 | J90: ='CC & HOH'!$W$15 -> 1 | K90: ='CC & HOH'!$X$15 -> 0.5 | L90: ='CC & HOH'!$Z$15 -> Tools | M90: ='CC & HOH'!$AA$15 -> 0 | N90: ='CC & HOH'!$AB$15 -> 0
A91: ='Summary (READ FIRST)'!$B$8 -> Supplier 1 | B91: ='Summary (READ FIRST)'!$B$11 -> English | C91: CC & HOH | D91: Quechua | E91: EPISODIC | F91: DISCOVERY/NON-SCRIPTED | G91: ='CC & HOH'!T15 -> 8 | H91: ='CC & HOH'!U15 -> 6 | J91: ='CC & HOH'!$W$15 -> 1 | K91: ='CC & HOH'!$X$15 -> 0.5 | L91: ='CC & HOH'!$Z$15 -> Tools | M91: ='CC & HOH'!$AA$15 -> 0 | N91: ='CC & HOH'!$AB$15 -> 0
A92: ='Summary (READ FIRST)'!$B$8 -> Supplier 1 | B92: ='Summary (READ FIRST)'!$B$11 -> English | C92: CC & HOH | D92: Quechua (Bolivia) | E92: FEATURE | F92: THEATRICAL RELEASE | G92: ='CC & HOH'!E16 -> 14 | H92: ='CC & HOH'!F16 -> 9 | J92: ='CC & HOH'!$W$16 -> 1 | K92: ='CC & HOH'!$X$16 -> 0 | L92: ='CC & HOH'!$Z$16 -> Automated system | M92: ='CC & HOH'!$AA$16 -> 0.1 | N92: ='CC & HOH'!$AB$16 -> Note 2
A93: ='Summary (READ FIRST)'!$B$8 -> Supplier 1 | B93: ='Summary (READ FIRST)'!$B$11 -> English | C93: CC & HOH | D93: Quechua (Bolivia) | E93: FEATURE | F93: NON-THEATRICAL - HOME ENT/STREAMING | G93: ='CC & HOH'!H16 -> 0 | H93: ='CC & HOH'!I16 -> 7 | J93: ='CC & HOH'!$W$16 -> 1 | K93: ='CC & HOH'!$X$16 -> 0 | L93: ='CC & HOH'!$Z$16 -> Automated system | M93: ='CC & HOH'!$AA$16 -> 0.1 | N93: ='CC & HOH'!$AB$16 -> Note 2
A94: ='Summary (READ FIRST)'!$B$8 -> Supplier 1 | B94: ='Summary (READ FIRST)'!$B$11 -> English | C94: CC & HOH | D94: Quechua (Bolivia) | E94: FEATURE | F94: NON-THEATRICAL - LINEAR BROADCAST | G94: ='CC & HOH'!K16 -> 9 | H94: ='CC & HOH'!L16 -> 4 | J94: ='CC & HOH'!$W$16 -> 1 | K94: ='CC & HOH'!$X$16 -> 0 | L94: ='CC & HOH'!$Z$16 -> Automated system | M94: ='CC & HOH'!$AA$16 -> 0.1 | N94: ='CC & HOH'!$AB$16 -> Note 2
A95: ='Summary (READ FIRST)'!$B$8 -> Supplier 1 | B95: ='Summary (READ FIRST)'!$B$11 -> English | C95: CC & HOH | D95: Quechua (Bolivia) | E95: EPISODIC | F95: HOME ENT/STREAMING | G95: ='CC & HOH'!N16 -> 11 | H95: ='CC & HOH'!O16 -> 7 | J95: ='CC & HOH'!$W$16 -> 1 | K95: ='CC & HOH'!$X$16 -> 0 | L95: ='CC & HOH'!$Z$16 -> Automated system | M95: ='CC & HOH'!$AA$16 -> 0.1 | N95: ='CC & HOH'!$AB$16 -> Note 2
A96: ='Summary (READ FIRST)'!$B$8 -> Supplier 1 | B96: ='Summary (READ FIRST)'!$B$11 -> English | C96: CC & HOH | D96: Quechua (Bolivia) | E96: EPISODIC | F96: BROADCAST/LINEAR | G96: ='CC & HOH'!Q16 -> 6 | H96: ='CC & HOH'!R16 -> 3 | J96: ='CC & HOH'!$W$16 -> 1 | K96: ='CC & HOH'!$X$16 -> 0 | L96: ='CC & HOH'!$Z$16 -> Automated system | M96: ='CC & HOH'!$AA$16 -> 0.1 | N96: ='CC & HOH'!$AB$16 -> Note 2
A97: ='Summary (READ FIRST)'!$B$8 -> Supplier 1 | B97: ='Summary (READ FIRST)'!$B$11 -> English | C97: CC & HOH | D97: Quechua (Bolivia) | E97: EPISODIC | F97: DISCOVERY/NON-SCRIPTED | G97: ='CC & HOH'!T16 -> 9 | H97: ='CC & HOH'!U16 -> 7 | J97: ='CC & HOH'!$W$16 -> 1 | K97: ='CC & HOH'!$X$16 -> 0 | L97: ='CC & HOH'!$Z$16 -> Automated system | M97: ='CC & HOH'!$AA$16 -> 0.1 | N97: ='CC & HOH'!$AB$16 -> Note 2
A98: ='Summary (READ FIRST)'!$B$8 -> Supplier 1 | B98: ='Summary (READ FIRST)'!$B$11 -> English | C98: CC & HOH | D98: Quechua (Ecuador) | E98: FEATURE | F98: THEATRICAL RELEASE | G98: ='CC & HOH'!E17 -> 0 | H98: ='CC & HOH'!F17 -> 4 | J98: ='CC & HOH'!$W$17 -> 1 | K98: ='CC & HOH'!$X$17 -> 0.5 | L98: ='CC & HOH'!$Z$17 -> Workflow | M98: ='CC & HOH'!$AA$17 -> 0.1 | N98: ='CC & HOH'!$AB$17 -> Note 2
A99: ='Summary (READ FIRST)'!$B$8 -> Supplier 1 | B99: ='Summary (READ FIRST)'!$B$11 -> English | C99: CC & HOH | D99: Quechua (Ecuador) | E99: FEATURE | F99: NON-THEATRICAL - HOME ENT/STREAMING | G99: ='CC & HOH'!H17 -> 11 | H99: ='CC & HOH'!I17 -> 6 | J99: ='CC & HOH'!$W$17 -> 1 | K99: ='CC & HOH'!$X$17 -> 0.5 | L99: ='CC & HOH'!$Z$17 -> Workflow | M99: ='CC & HOH'!$AA$17 -> 0.1 | N99: ='CC & HOH'!$AB$17 -> Note 2
A100: ='Summary (READ FIRST)'!$B$8 -> Supplier 1 | B100: ='Summary (READ FIRST)'!$B$11 -> English | C100: CC & HOH | D100: Quechua (Ecuador) | E100: FEATURE | F100: NON-THEATRICAL - LINEAR BROADCAST | G100: ='CC & HOH'!K17 -> 9 | H100: ='CC & HOH'!L17 -> 6 | J100: ='CC & HOH'!$W$17 -> 1 | K100: ='CC & HOH'!$X$17 -> 0.5 | L100: ='CC & HOH'!$Z$17 -> Workflow | M100: ='CC & HOH'!$AA$17 -> 0.1 | N100: ='CC & HOH'!$AB$17 -> Note 2
...

Sheet Summary (READ FIRST)
B2: WBD GCO Localization Long Form RFP
B3: Spring 2026
B5: Please fill out all fields in yellow before proceeding. Rates are to be shared in the subsequent tabs.
B7: Supplier name:
B8: Supplier 1
B10: Source language:
B11: English
B13: Assumptions
B14: 1. The source language is English unless otherwise noted. Vendors are welcome to submit rates for different source languages,
B15: but they must be submitted in separate copies of this file.
B16: 2. All rates are submitted in USD per minute.

Sheet Subtitling
C2: WBD GCO Localization RFP - MASTER Rate Card
C3: Please refer to the SLAs tab for detailed descriptions, definitions, and SLAs of each content type. Each section in the table is accompanied by a corresponding definitions table for clarity.
C4: Please provide a rate (USD) in the yellow cells.
E7: SUBTITLING SERVICES
E9: FEATURE | N9: EPISODIC
E10: THEATRICAL RELEASE | H10: NON-THEATRICAL - HOME ENT/STREAMING | K10: NON-THEATRICAL - LINEAR BROADCAST | N10: HOME ENT/STREAMING | Q10: BROADCAST/LINEAR | T10: DISCOVERY/NON-SCRIPTED | W10: Rush Charge 1 (%) | X10: Rush Charge 2 (%) | Z10: ADDITIONAL DISCOUNT OFFERING | AB10: Notes / Additional Assumptions
B11: No. | C11: Language | E11: Feature - Standard + | F11: Feature - Standard | H11: Feature - Standard + | I11: Feature - Standard | K11: Feature - Standard + | L11: Feature - Standard | N11: Episodic - Standard + | O11: Episodic - Standard | Q11: Episodic - Standard + | R11: Episodic - Standard | T11: Episodic - Standard + | U11: Episodic - Standard | W11: 1 day | X11: 2 days | Z11: Discount Offering Description - please provide additional discount offer based on use of any method that achieves efficiency and cost benefit (tools, workflow, etc). | AA11: % Discount Offered | AB11: Provide any additional information or assumptions
B12: 1 | C12: Aymara | E12: 26 | F12: 16 | H12: 28 | I12: 25 | K12: 22 | L12: 10 | N12: 23 | O12: 17 | Q12: 34 | T12: 19 | U12: 9 | W12: 1 | X12: 0.5 | Z12: Tools | AA12: 0.15 | AB12: Note 1
B13: 2 | C13: Mayan | E13: 20 | F13: 8 | H13: 21 | I13: 16 | L13: 12 | O13: 17 | Q13: 27 | R13: 20 | U13: 12 | W13: 1 | X13: 0.5 | Z13: Workflow
B14: 3 | C14: Portuguese (Brazil) | F14: 21 | H14: 27 | I14: 18 | K14: 38 | L14: 24 | N14: 38 | O14: 21 | R14: 19 | T14: 21 | AA14: 0.2
B15: 4 | C15: Quechua | E15: 27 | F15: 22 | H15: 27 | I15: 23 | K15: 36 | L15: 20 | O15: 15 | Q15: 26 | R15: 15 | T15: 38 | U15: 12 | W15: 1 | X15: 0.5 | Z15: Tools | AA15: 0.05 | AB15: Note 1
B16: 5 | C16: Quechua (Bolivia) | E16: 23 | I16: 25 | K16: 20 | N16: 16 | O16: 9 | Q16: 12 | R16: 8 | T16: 33 | U16: 21 | W16: 1 | X16: 0.5 | Z16: Automated system | AA16: 0.1
B17: 6 | C17: Quechua (Ecuador) | E17: 40 | F17: 20 | H17: 20 | I17: 17 | K17: 34 | L17: 18 | N17: 34 | W17: 1 | X17: 0.5 | Z17: Workflow | AA17: 0.1 | AB17: Note 1
B18: 7 | C18: Quechua (Peru) | E18: 29 | F18: 25 | H18: 37 | I18: 24 | K18: 25 | N18: 16 | O18: 13 | Q18: 40 | R18: 25 | T18: 27 | U18: 12 | AB18: Note 1
B19: 8 | C19: Spanish (Colombia) | F19: 22 | I19: 15 | K19: 35 | L19: 8 | O19: 8 | Q19: 21 | R19: 14 | T19: 23 | U19: 14 | W19: 1 | X19: 0.5 | Z19: Automated system | AA19: 0.2 | AB19: Note 1
B20: 9 | C20: Spanish (Mexico) | E20: 31 | H20: 39 | N20: 22 | O20: 15 | Q20: 33 | R20: 21 | U20: 21 | W20: 1 | X20: 0.5 | Z20: Tools | AA20: 0.05
B21: 10 | C21: Spanish (Latin American) | E21: 37 | F21: 23 | H21: 27 | I21: 19 | K21: 22 | L21: 14 | N21: 22 | Q21: 29 | T21: 26 | W21: 1 | X21: 0.5 | Z21: Workflow | AA21: 0.15 | AB21: Note 1
B22: 11 | C22: Zapotec | E22: 26 | F22: 18 | H22: 23 | I22: 17 | K22: 39 | L22: 19 | N22: 35 | O22: 22 | R22: 26 | T22: 20 | U22: 13 | W22: 1 | X22: 0.5 | Z22: Tools | AA22: 0.1 | AB22: Note 1

Sheet CC & HOH
C2: WBD GCO Localization RFP - MASTER Rate Card
C3: Please refer to the SLAs tab for detailed descriptions, definitions, and SLAs of each content type. Each section in the table is accompanied by a corresponding definitions table for clarity.
C4: Please provide a rate (USD) in the yellow cells.
E7: CC & HOH SERVICES
E9: FEATURE | N9: EPISODIC
E10: THEATRICAL RELEASE | H10: NON-THEATRICAL - HOME ENT/STREAMING | K10: NON-THEATRICAL - LINEAR BROADCAST | N10: HOME ENT/STREAMING | Q10: BROADCAST/LINEAR | T10: DISCOVERY/NON-SCRIPTED | W10: Rush Charge 1 (%) | X10: Rush Charge 2 (%) | Z10: ADDITIONAL DISCOUNT OFFERING | AB10: Notes / Additional Assumptions
B11: No. | C11: Language | E11: Feature - Standard + | F11: Feature - Standard | H11: Feature - Standard + | I11: Feature - Standard | K11: Feature - Standard + | L11: Feature - Standard | N11: Episodic - Standard + | O11: Episodic - Standard | Q11: Episodic - Standard + | R11: Episodic - Standard | T11: Episodic - Standard + | U11: Episodic - Standard | W11: 1 day | X11: 2 days | Z11: Discount Offering Description - please provide additional discount offer based on use of any method that achieves efficiency and cost benefit (tools, workflow, etc). | AA11: % Discount Offered | AB11: Provide any additional information or assumptions
B12: 1 | C12: Aymara | E12: 15 | F12: 7 | H12: 5 | I12: 4 | K12: 10 | L12: 9 | N12: 8 | O12: 3 | R12: 8 | T12: 12 | U12: 8 | W12: 1 | X12: 0.5 | Z12: Tools | AA12: 0.15 | AB12: Note 2
B13: 2 | C13: Mayan | E13: 17 | H13: 6 | K13: 11 | N13: 10 | O13: 6 | Q13: 12 | R13: 9 | T13: 8 | U13: 4 | X13: 0.5 | Z13: Workflow | AA13: 0.1 | AB13: Note 2
B14: 3 | C14: Portuguese (Brazil) | E14: 8 | F14: 3 | H14: 10 | I14: 4 | L14: 6 | N14: 13 | O14: 10 | Q14: 7 | U14: 8 | W14: 1 | X14: 0.5 | AA14: 0.05 | AB14: Note 2
B15: 4 | C15: Quechua | E15: 15 | F15: 10 | H15: 9 | I15: 7 | K15: 8 | L15: 7 | O15: 8 | Q15: 9 | R15: 5 | T15: 8 | U15: 6 | W15: 1 | X15: 0.5 | Z15: Tools
B16: 5 | C16: Quechua (Bolivia) | E16: 14 | F16: 9 | I16: 7 | K16: 9 | L16: 4 | N16: 11 | O16: 7 | Q16: 6 | R16: 3 | T16: 9 | U16: 7 | W16: 1 | Z16: Automated system | AA16: 0.1 | AB16: Note 2
B17: 6 | C17: Quechua (Ecuador) | F17: 4 | H17: 11 | I17: 6 | K17: 9 | L17: 6 | N17: 9 | O17: 7 | Q17: 8 | R17: 5 | T17: 9 | W17: 1 | X17: 0.5 | Z17: Workflow | AA17: 0.1 | AB17: Note 2
B18: 7 | C18: Quechua (Peru) | E18: 9 | F18: 8 | H18: 14 | I18: 3 | K18: 10 | N18: 11 | R18: 10 | T18: 5 | U18: 3 | W18: 1 | X18: 0.5 | Z18: Workflow | AB18: Note 2
B19: 8 | C19: Spanish (Colombia) | E19: 5 | F19: 3 | H19: 9 | I19: 6 | K19: 9 | L19: 7 | N19: 9 | O19: 5 | Q19: 15 | R19: 12 | T19: 9 | U19: 8 | W19: 1 | X19: 0.5 | AA19: 0.05
B20: 10 | C20: Spanish (Mexico) | E20: 5 | H20: 10 | I20: 4 | K20: 11 | L20: 8 | N20: 12 | O20: 7 | R20: 10 | U20: 10 | W20: 1 | X20: 0.5 | Z20: Tools | AA20: 0.05 | AB20: Note 2
B21: 11 | C21: Spanish (Latin American) | E21: 10 | F21: 8 | H21: 9 | L21: 5 | O21: 7 | Q21: 14 | R21: 8 | T21: 10 | U21: 5 | W21: 1 | X21: 0.5 | Z21: Workflow | AA21: 0.15 | AB21: Note 2
B22: 12 | C22: Zapotec | E22: 11 | F22: 10 | H22: 15 | I22: 9 | K22: 13 | L22: 5 | N22: 15 | O22: 8 | Q22: 8 | R22: 7 | T22: 15 | U22: 7 | X22: 0.5 | Z22: Tools | AA22: 0.1 | AB22: Note 2

Sheet Dubbing
C2: WBD GCO Localization RFP - MASTER Rate Card
C3: Please refer to the SLAs tab for detailed descriptions, definitions, and SLAs of each content type. Each section in the table is accompanied by a corresponding definitions table for clarity.
C4: Please provide a rate (USD) in the yellow cells.
E7: DUBBING SERVICES
E9: FEATURE | T9: EPISODIC
E10: THEATRICAL RELEASE | J10: NON-THEATRICAL | O10: NON-THEATRICAL - LINEAR BROADCAST | T10: EPISODIC SERIES | AA10: DISCOVERY/NON-SCRIPTED | AE10: Rush Charge 1 (%) | AF10: Rush Charge 2 (%) | AH10: ADDITIONAL DISCOUNT OFFERING | AJ10: Notes / Additional Assumptions
B11: No. | C11: Language | E11: Feature - Standard + DUBBING | F11: Feature - Standard + MIXING | G11: Feature - Standard DUBBING | H11: Feature - Standard MIXING | J11: Feature - Standard + DUBBING | K11: Feature - Standard + MIXING | L11: Feature - Standard DUBBING | M11: Feature - Standard MIXING | O11: Feature - Standard + DUBBING | P11: Feature - Standard + MIXING | Q11: Feature - Standard DUBBING | R11: Feature - Standard MIXING | T11: Single Episode - Standard + DUBBING | U11: Single Episode - Standard + MIXING | V11: Single Episode - Standard DUBBING | W11: Single Episode - Standard MIXING | X11: Full Series or Batched Episodes DUBBING | Y11: Full Series or Batched Episodes MIXING | AA11: Single Episode - Standard + | AB11: Single Episode - Standard | AC11: Full Series or Batched Episodes | AE11: 1 day | AF11: 2 days | AH11: Discount Offering Description - please provide additional discount offer based on use of any method that achieves efficiency and cost benefit (tools, workflow, etc). | AI11: % Discount Offered | AJ11: Provide any additional information or assumptions
B12: 1 | C12: Aymara | E12: 80 | F12: 70 | G12: 59 | H12: 51 | J12: 95 | K12: 89 | L12: 55 | M12: 33 | O12: 79 | P12: 71 | Q12: 69 | R12: 50 | T12: 71 | U12: 57 | V12: 60 | W12: 56 | X12: 63 | Y12: 69 | AA12: 56 | AB12: 55 | AC12: 84 | AE12: 1 | AF12: 0.5 | AH12: Tools | AI12: 0.15 | AJ12: Note 3
B13: 2 | C13: Mayan | E13: 81 | G13: 50 | H13: 50 | J13: 111 | K13: 118 | L13: 25 | M13: 72 | O13: 65 | P13: 55 | Q13: 54 | U13: 64 | V13: 74 | X13: 87 | AB13: 56 | AE13: 1 | AF13: 0.5 | AH13: Workflow | AI13: 0.1 | AJ13: Note 3
B14: 3 | C14: Portuguese (Brazil) | E14: 62 | F14: 114 | L14: 78 | M14: 63 | O14: 62 | P14: 96 | Q14: 56 | R14: 34 | T14: 90 | U14: 102 | W14: 56 | X14: 53 | Y14: 106 | AA14: 104 | AB14: 28 | AC14: 98 | AF14: 0.5 | AH14: Automated system | AI14: 0.2 | AJ14: Note 3
B15: 4 | C15: Quechua | G15: 35 | H15: 66 | J15: 54 | K15: 108 | L15: 27 | M15: 56 | Q15: 37 | R15: 55 | T15: 91 | U15: 64 | V15: 76 | W15: 52 | X15: 90 | Y15: 62 | AA15: 101 | AB15: 40 | AC15: 78 | AE15: 1 | AF15: 0.5
B16: 5 | C16: Quechua (Bolivia) | E16: 51 | F16: 50 | G16: 54 | H16: 37 | J16: 78 | K16: 119 | L16: 29 | O16: 70 | P16: 87 | Q16: 63 | R16: 69 | T16: 85 | U16: 119 | V16: 74 | Y16: 90 | AA16: 117 | AC16: 103 | AE16: 1 | AH16: Automated system | AI16: 0.1 | AJ16: Note 3
B17: 6 | C17: Quechua (Ecuador) | F17: 54 | G17: 67 | J17: 105 | M17: 34 | O17: 73 | P17: 82 | Q17: 70 | T17: 119 | W17: 45 | X17: 89 | AA17: 66 | AB17: 33 | AC17: 92 | AF17: 0.5 | AH17: Workflow | AI17: 0.1 | AJ17: Note 3
B18: 7 | C18: Quechua (Peru) | E18: 111 | H18: 25 | K18: 90 | L18: 37 | Q18: 56 | R18: 70 | T18: 110 | U18: 56 | V18: 38 | W18: 74 | X18: 52 | Y18: 92 | AB18: 25 | AC18: 111 | AE18: 1 | AF18: 0.5 | AH18: Workflow | AI18: 0.15
B19: 8 | C19: Spanish (Colombia) | F19: 56 | G19: 65 | J19: 73 | K19: 104 | L19: 50 | M19: 25 | O19: 119 | P19: 80 | Q19: 77 | R19: 42 | U19: 67 | V19: 60 | Y19: 103 | AA19: 98 | AB19: 77 | AE19: 1 | AJ19: Note 3
B20: 10 | C20: Spanish (Mexico) | E20: 89 | F20: 71 | H20: 68 | L20: 42 | M20: 77 | O20: 73 | P20: 82 | R20: 76 | T20: 120 | U20: 99 | V20: 79 | W20: 69 | X20: 83 | Y20: 99 | AA20: 53 | AB20: 33 | AC20: 95 | AE20: 1 | AF20: 0.5 | AH20: Tools | AI20: 0.05 | AJ20: Note 3
B21: 11 | C21: Spanish (Latin American) | G21: 68 | H21: 70 | J21: 59 | K21: 78 | P21: 89 | Q21: 27 | R21: 58 | T21: 95 | X21: 115 | AC21: 113 | AF21: 0.5 | AH21: Workflow | AI21: 0.15 | AJ21: Note 3
B22: 12 | C22: Zapotec | E22: 56 | F22: 61 | G22: 28 | H22: 75 | J22: 79 | K22: 54 | L22: 76 | M22: 46 | O22: 111 | P22: 119 | R22: 60 | T22: 102 | U22: 59 | V22: 49 | W22: 72 | X22: 59 | Y22: 59 | AA22: 77 | AB22: 66 | AC22: 109 | AE22: 1 | AF22: 0.5 | AH22: Tools | AI22: 0.1 | AJ22: Note 3

Sheet Audio Desc.
C2: WBD GCO Localization RFP - MASTER Rate Card
C3: Please refer to the SLAs tab for detailed descriptions, definitions, and SLAs of each content type. Each section in the table is accompanied by a corresponding definitions table for clarity.
C4: Please provide a rate (USD) in the yellow cells.
E7: AUDIO DESCRIPTION SERVICES
E9: FEATURE | T9: EPISODIC
E10: THEATRICAL RELEASE | J10: NON-THEATRICAL | O10: NON-THEATRICAL - LINEAR BROADCAST | T10: EPISODIC SERIES | AA10: DISCOVERY/NON-SCRIPTED | AE10: Rush Charge 1 (%) | AF10: Rush Charge 2 (%) | AH10: ADDITIONAL DISCOUNT OFFERING | AJ10: Notes / Additional Assumptions
B11: No. | C11: Language | E11: Feature - Standard + DUBBING | F11: Feature - Standard + MIXING | G11: Feature - Standard DUBBING | H11: Feature - Standard MIXING | J11: Feature - Standard + DUBBING | K11: Feature - Standard + MIXING | L11: Feature - Standard DUBBING | M11: Feature - Standard MIXING | O11: Feature - Standard + DUBBING | P11: Feature - Standard + MIXING | Q11: Feature - Standard DUBBING | R11: Feature - Standard MIXING | T11: Single Episode - Standard + DUBBING | U11: Single Episode - Standard + MIXING | V11: Single Episode - Standard DUBBING | W11: Single Episode - Standard MIXING | X11: Full Series or Batched Episodes DUBBING | Y11: Full Series or Batched Episodes MIXING | AA11: Single Episode - Standard + | AB11: Single Episode - Standard | AC11: Full Series or Batched Episodes | AE11: 1 day | AF11: 2 days | AH11: Discount Offering Description - please provide additional discount offer based on use of any method that achieves efficiency and cost benefit (tools, workflow, etc). | AI11: % Discount Offered | AJ11: Provide any additional information or assumptions
B12: 1 | C12: Aymara | E12: 86 | F12: 85 | G12: 26 | H12: 17 | J12: 43 | K12: 83 | L12: 16 | M12: 17 | O12: 42 | P12: 79 | Q12: 52 | R12: 15 | T12: 85 | U12: 93 | V12: 60 | W12: 49 | X12: 96 | Y12: 34 | AA12: 61 | AB12: 33 | AC12: 48 | AE12: 1 | AF12: 0.5 | AH12: Tools | AI12: 0.15 | AJ12: Note 4
B13: 2 | C13: Mayan | E13: 86 | F13: 44 | G13: 55 | H13: 36 | J13: 82 | K13: 47 | L13: 17 | M13: 86 | O13: 17 | P13: 45 | Q13: 94 | R13: 71 | T13: 43 | U13: 96 | V13: 36 | W13: 44 | X13: 90 | Y13: 83 | AA13: 69 | AB13: 52 | AC13: 55 | AE13: 1 | AF13: 0.5 | AI13: 0.1 | AJ13: Note 4
B14: 3 | C14: Portuguese (Brazil) | E14: 37 | G14: 17 | H14: 29 | J14: 50 | K14: 44 | L14: 23 | O14: 20 | Q14: 69 | R14: 96 | T14: 30 | U14: 60 | V14: 95 | AA14: 91 | AB14: 31 | AF14: 0.5 | AH14: Automated system | AJ14: Note 4
B15: 4 | C15: Quechua | E15: 87 | F15: 48 | G15: 59 | H15: 56 | J15: 82 | K15: 43 | M15: 68 | O15: 43 | P15: 30 | Q15: 69 | T15: 46 | W15: 79 | X15: 98 | Y15: 62 | AB15: 37 | AC15: 92 | AE15: 1 | AF15: 0.5 | AH15: Tools | AI15: 0.05 | AJ15: Note 4
B16: 5 | C16: Quechua (Bolivia) | E16: 80 | F16: 77 | G16: 56 | H16: 48 | L16: 15 | M16: 83 | O16: 31 | P16: 57 | Q16: 98 | R16: 81 | T16: 53 | U16: 85 | V16: 37 | X16: 70 | AA16: 88 | AB16: 47 | AC16: 53 | AE16: 1 | AI16: 0.1 | AJ16: Note 4
B17: 6 | C17: Quechua (Ecuador) | E17: 36 | F17: 92 | H17: 26 | J17: 52 | K17: 45 | L17: 32 | M17: 71 | O17: 27 | P17: 18 | R17: 84 | V17: 85 | W17: 50 | X17: 92 | Y17: 53 | AA17: 76 | AF17: 0.5 | AH17: Workflow
B18: 7 | C18: Quechua (Peru) | G18: 26 | H18: 49 | J18: 88 | K18: 38 | L18: 57 | M18: 88 | O18: 35 | P18: 29 | Q18: 59 | R18: 61 | T18: 31 | U18: 32 | V18: 76 | W18: 59 | X18: 43 | Y18: 65 | AA18: 40 | AB18: 34 | AC18: 99 | AE18: 1 | AF18: 0.5 | AH18: Workflow | AI18: 0.15 | AJ18: Note 4
B19: 8 | C19: Spanish (Colombia) | E19: 50 | F19: 86 | G19: 58 | H19: 20 | J19: 80 | K19: 43 | L19: 60 | M19: 98 | P19: 35 | Q19: 87 | U19: 49 | V19: 57 | W19: 38 | X19: 44 | AB19: 42 | AC19: 30 | AE19: 1 | AH19: Automated system | AI19: 0.2 | AJ19: Note 4
B20: 10 | C20: Spanish (Mexico) | E20: 55 | F20: 99 | G20: 17 | H20: 44 | O20: 52 | P20: 50 | Q20: 71 | R20: 50 | T20: 33 | X20: 37 | Y20: 91 | AA20: 78 | AB20: 57 | AF20: 0.5 | AJ20: Note 4
B21: 11 | C21: Spanish (Latin American) | E21: 72 | F21: 32 | G21: 31 | J21: 99 | K21: 40 | L21: 49 | M21: 90 | O21: 39 | P21: 19 | R21: 32 | T21: 55 | U21: 71 | V21: 91 | W21: 66 | X21: 85 | Y21: 77 | AA21: 68 | AB21: 37 | AC21: 87 | AE21: 1 | AF21: 0.5 | AH21: Workflow | AI21: 0.15
B22: 12 | C22: Zapotec | E22: 48 | F22: 81 | G22: 40 | H22: 38 | J22: 74 | K22: 23 | L22: 20 | M22: 50 | O22: 22 | P22: 20 | Q22: 64 | R22: 35 | T22: 18 | U22: 100 | V22: 56 | W22: 92 | X22: 95 | Y22: 44 | AA22: 55 | AB22: 52 | AC22: 71 | AE22: 1 | AH22: Tools | AI22: 0.1 | AJ22: Note 4

Sheet VO
C2: WBD GCO Localization RFP - MASTER Rate Card
C3: Please refer to the SLAs tab for detailed descriptions, definitions, and SLAs of each content type. Each section in the table is accompanied by a corresponding definitions table for clarity.
C4: Please provide a rate (USD) in the yellow cells.
E7: VOICEOVER SERVICES
E9: FEATURE | T9: EPISODIC
E10: LIMITED THEATRICAL | J10: NON-THEATRICAL | O10: NON-THEATRICAL - LINEAR BROADCAST | T10: EPISODIC SERIES | AA10: DISCOVERY/NON-SCRIPTED | AE10: Rush Charge 1 (%) | AF10: Rush Charge 2 (%) | AH10: ADDITIONAL DISCOUNT OFFERING | AJ10: Notes / Additional Assumptions
B11: No. | C11: Language | E11: Feature - Standard + DUBBING | F11: Feature - Standard + MIXING | G11: Feature - Standard DUBBING | H11: Feature - Standard MIXING | J11: Feature - Standard + DUBBING | K11: Feature - Standard + MIXING | L11: Feature - Standard DUBBING | M11: Feature - Standard MIXING | O11: Feature - Standard + DUBBING | P11: Feature - Standard + MIXING | Q11: Feature - Standard DUBBING | R11: Feature - Standard MIXING | T11: Single Episode - Standard + DUBBING | U11: Single Episode - Standard + MIXING | V11: Single Episode - Standard DUBBING | W11: Single Episode - Standard MIXING | X11: Full Series or Batched Episodes DUBBING | Y11: Full Series or Batched Episodes MIXING | AA11: Single Episode - Standard + | AB11: Single Episode - Standard | AC11: Full Series or Batched Episodes | AE11: 1 day | AF11: 2 days | AH11: Discount Offering Description - please provide additional discount offer based on use of any method that achieves efficiency and cost benefit (tools, workflow, etc). | AI11: % Discount Offered | AJ11: Provide any additional information or assumptions
B12: 1 | C12: Aymara | E12: 41 | F12: 57 | G12: 29 | H12: 40 | J12: 59 | K12: 60 | L12: 44 | M12: 30 | O12: 42 | P12: 45 | Q12: 34 | R12: 46 | T12: 41 | U12: 60 | V12: 24 | W12: 30 | X12: 57 | Y12: 45 | AA12: 67 | AB12: 43 | AC12: 39 | AE12: 1 | AF12: 0.5 | AH12: Tools | AI12: 0.15 | AJ12: Note 5
B13: 2 | C13: Mayan | E13: 41 | F13: 54 | K13: 47 | M13: 53 | O13: 56 | P13: 50 | R13: 29 | T13: 48 | U13: 41 | V13: 40 | W13: 34 | X13: 78 | Y13: 79 | AB13: 41 | AC13: 73 | AE13: 1 | AF13: 0.5 | AH13: Workflow | AI13: 0.1 | AJ13: Note 5
B14: 3 | C14: Portuguese (Brazil) | E14: 47 | F14: 54 | G14: 56 | H14: 20 | J14: 43 | K14: 35 | L14: 32 | M14: 22 | P14: 71 | Q14: 49 | R14: 20 | U14: 45 | W14: 60 | AA14: 30 | AC14: 73 | AE14: 1 | AF14: 0.5 | AI14: 0.2 | AJ14: Note 5
B15: 4 | C15: Quechua | E15: 53 | F15: 37 | G15: 59 | H15: 27 | J15: 37 | L15: 34 | M15: 46 | O15: 71 | P15: 69 | Q15: 53 | R15: 33 | T15: 55 | V15: 23 | W15: 39 | X15: 66 | Y15: 36 | AA15: 31 | AB15: 32 | AC15: 55 | AH15: Tools | AI15: 0.05
B16: 5 | C16: Quechua (Bolivia) | E16: 79 | G16: 51 | H16: 32 | J16: 46 | K16: 36 | L16: 24 | O16: 45 | Q16: 59 | U16: 62 | V16: 41 | X16: 44 | AA16: 63 | AB16: 24 | AE16: 1 | AF16: 0.5 | AH16: Automated system | AJ16: Note 5
B17: 6 | C17: Quechua (Ecuador) | F17: 52 | G17: 42 | K17: 73 | M17: 54 | O17: 53 | P17: 74 | Q17: 23 | R17: 32 | T17: 39 | U17: 77 | V17: 31 | W17: 50 | X17: 53 | Y17: 50 | AA17: 73 | AB17: 55 | AC17: 58 | AE17: 1 | AF17: 0.5 | AI17: 0.1 | AJ17: Note 5
B18: 7 | C18: Quechua (Peru) | E18: 77 | F18: 49 | G18: 25 | H18: 41 | J18: 55 | K18: 46 | L18: 36 | M18: 46 | P18: 59 | Q18: 29 | R18: 43 | T18: 40 | U18: 62 | V18: 25 | W18: 56 | Y18: 32 | AA18: 61 | AC18: 62 | AH18: Workflow | AI18: 0.15 | AJ18: Note 5
B19: 8 | C19: Spanish (Colombia) | E19: 73 | H19: 39 | J19: 58 | L19: 50 | O19: 77 | P19: 57 | R19: 28 | T19: 51 | W19: 37 | X19: 33 | Y19: 37 | AA19: 60 | AB19: 27 | AC19: 55 | AE19: 1 | AF19: 0.5 | AH19: Automated system | AI19: 0.2 | AJ19: Note 5
B20: 10 | C20: Spanish (Mexico) | E20: 62 | F20: 42 | G20: 21 | J20: 46 | K20: 53 | L20: 23 | M20: 29 | O20: 37 | Q20: 27 | R20: 27 | T20: 50 | U20: 45 | V20: 54 | W20: 43 | X20: 78 | AB20: 34 | AC20: 40 | AE20: 1
B21: 11 | C21: Spanish (Latin American) | E21: 50 | F21: 46 | G21: 27 | H21: 21 | K21: 54 | P21: 58 | Q21: 46 | U21: 75 | V21: 43 | W21: 29 | Y21: 51 | AA21: 68 | AB21: 59 | AF21: 0.5 | AH21: Workflow | AI21: 0.15 | AJ21: Note 5
B22: 12 | C22: Zapotec | E22: 51 | F22: 76 | G22: 50 | H22: 44 | J22: 43 | L22: 33 | M22: 42 | O22: 57 | P22: 45 | Q22: 30 | R22: 59 | T22: 69 | U22: 60 | V22: 37 | W22: 37 | X22: 74 | Y22: 51 | AA22: 70 | AB22: 28 | AC22: 69 | AE22: 1 | AF22: 0.5 | AH22: Tools | AI22: 0.1 | AJ22: Note 5

Sheet SLAs and Definitions >>
B2: This page intentionally left blank.

Sheet SLAs
B2: WBD GCO Localization RFP - SLAs
B3: Below are the correlating SLAs for each requested service. There are a total of 5 tables - Subtitilng, CC&HOH, Dubbing, Audio Description, and Voiceover.
B7: SUBTITLING SERVICES
D10: FEATURE | J10: EPISODIC
C11: Type of work | D11: THEATRICAL | F11: ALL CONTENT TYPES - HOME ENT/STREAMING Home Entertainment, Broadcast, SVOD, VOD… | H11: ALL CONTENT TYPES - LINEAR/BROADCAST Linear Broadcast Servicing Channel. | J11: ALL CONTENT TYPES - HOME ENT/STREAMING Home Entertainment, Broadcast, SVOD, VOD… | L11: ALL CONTENT TYPES - LINEAR/BROADCAST Linear Broadcast servicing Channel | N11: DISCOVERY / NON-SCRIPTED
C12: SLA | D12: Standard+ | E12: Standard | F12: Standard+ | G12: Standard | H12: Standard + | I12: Standard | J12: Standard + | K12: Standard | L12: Standard + | M12: Standard | N12: Standard + | O12: Standard
C13: Turnaround Time in Calendar Days - Final Materials to vendor and Localized Content Delivery | D13: 6-9 days for Feature | E13: ≥ 28 days for Feature | F13: 6-9 days for Feature | G13: ≥ 10 days for Feature | H13: 6 - 10 calendar days | I13: ≥ 11 calendar days | J13: 3-5 calendar days for Episodic (from final) | K13: ≥ 6 calendar days for Episodic (Half Hour) | L13: 3- 9 calendar days | M13: ≥ 10 calendar days | N13: 3-13 calendar days | O13: ≥ 14 calendar days
B14: Localization Function | C14: Activity | D14: Warner Bros. Discovery Consolidated Subtitling Rates Cards are based on the below service requirements
B15: SOURCE MATERIALS SUPPLIED FROM CLIENT | C15: Audio & Visual Content Prelim (Network, Locked) or Final (Low-Res or HD digital file; no physical) | D15: Locked Prelim and Final AV Materials (Note - addtional iterations can be can be provided by client if required) | E15: Final AV Materials | F15: Prelim (if required) and Final AV Materials | G15: Final AV Materials | H15: Prelim (if required) and Final AV Materials | I15: Final AV Materials | J15: Prelim (if required) and Final AV Materials | K15: Final AV Materials | L15: Prelim (if required) and Final AV Materials | M15: Final AV Materials | N15: Prelim (if required) and Final AV Materials | O15: Final AV Materials
C16: Scripts & Creative Documentation: Original Version Language (Ref Source Materials Definition Tab) | D16: Client to provide. If no English script or equivalent provided, additional charge may apply | E16: Client to provide. If no English script or equivalent provided, additional charge may apply | F16: Client to provide. If no English script or equivalent provided, additional charge may apply | G16: Client to provide. If no English script or equivalent provided, additional charge may apply | H16: Client to provide. If no English script or equivalent provided, additional charge may apply | I16: Client to provide. If no English script or equivalent provided, additional charge may apply | J16: Client to provide. If no English script or equivalent provided, additional charge may apply | K16: Client to provide. If no English script or equivalent provided, additional charge may apply | L16: Client to provide. If no English script or equivalent provided, additional charge may apply | M16: Client to provide. If no English script or equivalent provided, additional charge may apply | N16: Client to provide. If no English script or equivalent provided, additional charge may apply | O16: Client to provide. If no English script or equivalent provided, additional charge may apply
C17: Final Video Master When Video Master deliverable required | D17: Client to provide error free final video & audio, balanced M&E, textless at tail (if needed). Vendor to perform 3-point check QC upon receipt, noting issues within 48 hours | E17: Client to provide error free final video & audio, balanced M&E, textless at tail (if needed). Vendor to perform 3-point check QC upon receipt, noting issues within 48 hours | F17: Client to provide error free final video & audio, balanced M&E, textless at tail (if needed). Vendor to perform 3-point check QC upon receipt, noting issues within 48 hours | G17: Client to provide error free final video & audio, balanced M&E, textless at tail (if needed). Vendor to perform 3-point check QC upon receipt, noting issues within 48 hours | H17: Client to provide error free final video & audio, balanced M&E, textless at tail (if needed). Vendor to perform 3-point check QC upon receipt, noting issues within 48 hours | I17: Client to provide error free final video & audio, balanced M&E, textless at tail (if needed). Vendor to perform 3-point check QC upon receipt, noting issues within 48 hours | J17: Client to provide error free final video & audio, balanced M&E, textless at tail (if needed). Vendor to perform 3-point check QC upon receipt, noting issues within 48 hours | K17: Client to provide error free final video & audio, balanced M&E, textless at tail (if needed). Vendor to perform 3-point check QC upon receipt, noting issues within 48 hours | L17: Client to provide error free final video & audio, balanced M&E, textless at tail (if needed). Vendor to perform 3-point check QC upon receipt, noting issues within 48 hours | M17: Client to provide error free final video & audio, balanced M&E, textless at tail (if needed). Vendor to perform 3-point check QC upon receipt, noting issues within 48 hours | N17: Client to provide error free final video & audio Vendor to perform 3-point check QC upon receipt, noting issues within 48 hours | O17: Client to provide error free final video & audio Vendor to perform 3-point check QC upon receipt, noting issues within 48 hours
B18: SECURITY TIERS | C18: Applying security measures to Reference Materials (Ref Security Tiers Definition Tab) | D18: Tier MAX or 0. If Tier MAX required, additional charge may apply (security level to be discussed with client on each title) | E18: Tier MAX or 0. If Tier MAX required, additional charge may apply (security level to be discussed with client on each title) | F18: Vendor to provide secure access for translators / approvers to subtitling SaaS Platform. Additional watermarking must be applied by the system to ensure access is traceable to those granted access. | G18: Vendor to provide secure access for translators / approvers to subtitling SaaS Platform. Additional watermarking must be applied by the system to ensure access is traceable to those granted access. | H18: Vendor to provide secure access for translators / approvers to subtitling SaaS Platform. Additional watermarking must be applied by the system to ensure access is traceable to those granted access. | I18: Vendor to provide secure access for translators / approvers to subtitling SaaS Platform. Additional watermarking must be applied by the system to ensure access is traceable to those granted access. | J18: Vendor to provide secure access for translators / approvers to subtitling SaaS Platform. Additional watermarking must be applied by the system to ensure access is traceable to those granted access. | K18: Vendor to provide secure access for translators / approvers to subtitling SaaS Platform. Additional watermarking must be applied by the system to ensure access is traceable to those granted access. | L18: Vendor to provide secure access for translators / approvers to subtitling SaaS Platform. Additional watermarking must be applied by the system to ensure access is traceable to those granted access. | M18: Vendor to provide secure access for translators / approvers to subtitling SaaS Platform. Additional watermarking must be applied by the system to ensure access is traceable to those granted access. | N18: Vendor to provide secure access for translators / approvers to subtitling SaaS Platform. Additional watermarking must be applied by the system to ensure access is traceable to those granted access. | O18: Vendor to provide secure access for translators / approvers to subtitling SaaS Platform. Additional watermarking must be applied by the system to ensure access is traceable to those granted access.
B19: TRANSLATION | C19: Translator selection | D19: Client Translator selection. If vendor translator is required to ensure native speaker translator. | E19: Client Translator selection. If vendor translator is required to ensure native speaker translator. | F19: Vendor responsible for providing Native Speaker translator, client reserves the right to participate in translator selection. | G19: Vendor responsible for providing Native Speaker translator, client reserves the right to participate in translator selection | H19: Vendor responsible for providing Native Speaker translator. | I19: Vendor responsible for providing Native Speaker translator. | J19: Vendor responsible for providing Native Speaker translator, client reserves the right to participate in translator selection. | K19: Vendor responsible for providing Native Speaker translator, client reserves the right to participate in translator selection | L19: Vendor responsible for providing Native Speaker translator. | M19: Vendor responsible for providing Native Speaker translator. | N19: Vendor responsible for providing Native Speaker translator. | O19: Vendor responsible for providing Native Speaker translator.
C20: Linguistic & Technical QC | D20: Native Speaker Linguistic QC & Full Technical QC included. Changes to be approved by client translator/approver | E20: Native Speaker Linguistic QC & Full Technical QC included. Changes to be approved by client translator/approver | F20: Native Speaker Linguistic QC & Full Linear Technical QC included. | G20: Native Speaker Linguistic QC & Full Linear Technical QC included. | H20: Linguistic QC possible at additional charge. Technical QC included | I20: Linguistic QC possible at additional charge. Technical QC included | J20: Native Speaker Linguistic QC & Full Linear Technical QC included. | K20: Native Speaker Linguistic QC & Full Linear Technical QC included. | L20: Linguistic QC possible at additional charge. Technical QC included | M20: Linguistic QC possible at additional charge. Technical QC included | N20: Linguistic QC possible at additional charge. Technical QC included | O20: Linguistic QC possible at additional charge. Technical QC included
C21: Compliance | D21: Censorship and / or softening of language for certain content may be required. Any potential sensitivities must be flagged to client, especially children's content. | E21: Censorship and / or softening of language for certain content may be required. Any potential sensitivities must be flagged to client, especially children's content. | F21: Censorship and / or softening of language for certain content may be required. Any potential sensitivities must be flagged to client, especially children's content. | G21: Censorship and / or softening of language for certain content may be required. Any potential sensitivities must be flagged to client, especially children's content. | H21: Censorship and / or softening of language for certain content may be required. Any potential sensitivities must be flagged to client, especially children's content. | I21: Censorship and / or softening of language for certain content may be required. Any potential sensitivities must be flagged to client, especially children's content. | J21: Censorship and / or softening of language for certain content may be required. Any potential sensitivities must be flagged to client, especially children's content. | K21: Censorship and / or softening of language for certain content may be required. Any potential sensitivities must be flagged to client, especially children's content. | L21: Censorship and / or softening of language for certain content may be required. Any potential sensitivities must be flagged to client, especially children's content. | M21: Censorship and / or softening of language for certain content may be required. Any potential sensitivities must be flagged to client, especially children's content. | N21: NA | O21: NA
C22: Translator's credit | D22: To be included on all subtitle files, unless client advises otherwise. | E22: To be included on all subtitle files, unless client advises otherwise. | F22: To be included on all subtitle files, unless client advises otherwise. | G22: To be included on all subtitle files, unless client advises otherwise. | H22: To be included on all subtitle files, unless client advises otherwise. | I22: To be included on all subtitle files, unless client advises otherwise. | J22: To be included on all subtitle files, unless client advises otherwise. | K22: To be included on all subtitle files, unless client advises otherwise. | L22: To be included on all subtitle files, unless client advises otherwise. | M22: To be included on all subtitle files, unless client advises otherwise. | N22: To be included on all subtitle files, unless client advises otherwise. | O22: To be included on all subtitle files, unless client advises otherwise.
B23: CLIENT APPROVAL | C23: Subtitles Approvals Non-Physical release | D23: Where client approvals are required, time for the approvals must be pre-agreed. If approvals are not received within agreed timelines, client is notified to determine next steps i.e extend deadline, proceed, etc | E23: Where client approvals are required, time for the approvals must be pre-agreed. If approvals are not received within agreed timelines, the timeline can be extended as appropriate and as agreed by both parties. | F23: Where client approvals are required, time for the approvals must be pre-agreed. If approvals are not received within agreed timelines, client is notified to determine next steps i.e extend deadline, proceed, etc | G23: Where client approvals are required, time for the approvals must be pre-agreed. If approvals are not received within agreed timelines, the timeline can be extended as appropriate and as agreed by both parties. | H23: No Client Approvals | I23: No Client Approvals | J23: Where client approvals are required, time for the approvals must be pre-agreed. If approvals are not received within agreed timelines, client is notified to determine next steps i.e extend deadline, proceed, etc | K23: Where client approvals are required, time for the approvals must be pre-agreed. If approvals are not received within agreed timelines, the timeline can be extended as appropriate and as agreed by both parties. Included in price. | L23: No Client Approvals | M23: No Client Approvals | N23: Client Approvals may be requested at no additional charge. | O23: Client Approvals may be requested at no additional charge.
C24: Subtitles Approvals Physical release | D24: Where client approvals are required, time for the approvals must be pre-agreed. If approvals are not received within agreed timelines, vendor notifies client to determine next steps i.e extend deadline, proceed, etc Included in price. All subs for Home Video release to be sent to the emulation QC vendor for pre-check before delivering to authoring. Pre-Delivery is done as XML with .BMP associated with content related media. | E24: Where client approvals are required, time for the approvals must be pre-agreed. If approvals are not received within agreed timelines, the timeline can be extended as appropriate and as agreed by both parties. Included in price. All subs for Home Video release to be sent to the emulation QC vendor for pre-check before delivering to authoring. Pre-Delivery is done as XML with .BMP associated with content related media. | F24: Where client approvals are required, time for the approvals must be pre-agreed. If approvals are not received within agreed timelines, vendor notifies client to determine next steps i.e extend deadline, proceed, etc Included in price. All subs for Home Video release to be sent to the emulation QC vendor for pre-check before delivering to authoring. Pre-Delivery is done as XML with .BMP associated with content related media. | G24: Where client approvals are required, time for the approvals must be pre-agreed. If approvals are not received within agreed timelines, the timeline can be extended as appropriate and as agreed by both parties. Included in price. All subs for Home Video release to be sent to the emulation QC vendor for pre-check before delivering to authoring. Pre-Delivery is done as XML with .BMP associated with content related media. | H24: No Client Approvals | I24: No Client Approvals | J24: Where client approvals are required, time for the approvals must be pre-agreed. If approvals are not received within agreed timelines, vendor notifies client to determine next steps i.e extend deadline, proceed, etc Included in price. | K24: Where client approvals are required, time for the approvals must be pre-agreed. If approvals are not received within agreed timelines, the timeline can be extended as appropriate and as agreed by both parties. Included in price. | L24: No Client Approvals | M24: No Client Approvals | N24: No Client Approvals | O24: No Client Approvals
B25: SONGS | C25: Songs Translation | D25: If plot pertinent, and has both been requested by client and confirmation lyrics have been cleared for translation. Additional charge. | E25: If plot pertinent, and has both been requested by client and confirmation lyrics have been cleared for translation. Additional charge. | F25: Plot pertinent and cleared lyrics will be subtitled If requested by Client | G25: Plot pertinent and cleared lyrics will be subtitled If requested by Client | H25: Plot pertinent and cleared lyrics will be subtitled If requested by Client | I25: Plot pertinent and cleared lyrics will be subtitled If requested by Client | J25: Plot pertinent and cleared lyrics will be subtitled If requested by Client | K25: Plot pertinent and cleared lyrics will be subtitled If requested by Client | L25: Plot pertinent and cleared lyrics will be subtitled If requested by Client | M25: Plot pertinent and cleared lyrics will be subtitled If requested by Client | N25: NA | O25: NA
B26: DELIVERABLES | C26: Format | D26: Includes one set of final deliverables to multiple end users, formats to be agreed with client. Maybe change "to be agreed" to "as currently agreed". Upload to 2/3 x endpoints? DETE/NEST/Keystone. HBO uploading to more than 2. Could have 1 format and 1 delivery with the assumption that in the future we will insource additional deliverables/endpoints in the future. | E26: Includes one set of final deliverables to multiple end users, formats to be agreed with client. | F26: Includes one set of final deliverables to multiple end users, formats to be agreed with client. | G26: Includes one set of final deliverables to multiple end users, formats to be agreed with client. | H26: Includes one set of final deliverables to multiple end users, formats to be agreed with client. | I26: Includes one set of final deliverables to multiple end users, formats to be agreed with client. | J26: Includes one set of final deliverables to multiple end users, formats to be agreed with client. | K26: Includes one set of final deliverables to multiple end users, formats to be agreed with client. | L26: Includes one set of final deliverables to multiple end users, formats to be agreed with client. | M26: Includes one set of final deliverables to multiple end users, formats to be agreed with client. | N26: Includes one set of final deliverables to multiple end users, formats to be agreed with client. | O26: Includes one set of final deliverables to multiple end users, formats to be agreed with client.
B27: ISSUES / REDELIVERIES | C27: Non-Physical release | D27: Vendor has an obligation to deliver accurate translated subtitle files, (this does not cover subjective difference). Egregious creative errors or technical errors must be remediated by vendor. | E27: Vendor has an obligation to deliver accurate translated subtitle files, (this does not cover subjective difference). Egregious creative errors or technical errors must be remediated by vendor. | F27: Vendor has an obligation to deliver accurate translated subtitle files, (this does not cover subjective difference). Egregious creative errors or technical errors must be remediated by vendor. | G27: Vendor has an obligation to deliver accurate translated subtitle files, (this does not cover subjective difference). Egregious creative errors or technical errors must be remediated by vendor. | H27: Vendor has an obligation to deliver accurate translated subtitle files, (this does not cover subjective difference). Egregious creative errors or technical errors must be remediated by vendor. | I27: Vendor has an obligation to deliver accurate translated subtitle files, (this does not cover subjective difference). Egregious creative errors or technical errors must be remediated by vendor. | J27: Vendor has an obligation to deliver accurate translated subtitle files, (this does not cover subjective difference). Egregious creative errors or technical errors must be remediated by vendor. | K27: Vendor has an obligation to deliver accurate translated subtitle files, (this does not cover subjective difference). Egregious creative errors or technical errors must be remediated by vendor. | L27: Vendor has an obligation to deliver accurate translated subtitle files, (this does not cover subjective difference). Egregious creative errors or technical errors must be remediated by vendor. | M27: Vendor has an obligation to deliver accurate translated subtitle files, (this does not cover subjective difference). Egregious creative errors or technical errors must be remediated by vendor. | N27: Vendor has an obligation to deliver accurate translated subtitle files, (this does not cover subjective difference). Egregious creative errors or technical errors must be remediated by vendor. | O27: Vendor has an obligation to deliver accurate translated subtitle files, (this does not cover subjective difference). Egregious creative errors or technical errors must be remediated by vendor.
C28: Physical release | D28: Upon receipt of QC report from 3rd party vendor, fixes will be redelivered within 48 hours. | E28: Upon receipt of QC report from 3rd party vendor, fixes will be redelivered within 48 hours. | F28: Upon receipt of QC report from 3rd party vendor, fixes will be redelivered within 48 hours. | G28: Upon receipt of QC report from 3rd party vendor, fixes will be redelivered within 48 hours. | H28: N/A | I28: N/A | J28: Upon receipt of QC report from 3rd party vendor, fixes will be redelivered within 48 hours. | K28: Upon receipt of QC report from 3rd party vendor, fixes will be redelivered within 48 hours. | L28: N/A | M28: N/A | N28: NA | O28: NA
B29: ARCHIVE/ BACK UP | C29: Additional deliverables | D29: Per WBD requirements. Additional charge may apply | E29: Per WBD requirements. Additional charge may apply | F29: Per WBD requirements. Additional charge may apply | G29: Per WBD requirements. Additional charge may apply | H29: Vendor Archive included | I29: Vendor Archive included | J29: Per WBD requirements. Additional charge may apply | K29: Per WBD requirements. Additional charge may apply | L29: Vendor Archive included | M29: Vendor Archive included | N29: Vendor Archive included | O29: Vendor Archive included
B30: BUYOUT RIGHTS | C30: Rights to be secured by vendor on behalf of WBD client | D30: All rights, all formats in perpetuity, theatrical rights included (or the equivalent legal requirements in each territory). | E30: All rights, all formats in perpetuity, theatrical rights included (or the equivalent legal requirements in each territory). | F30: Maximum copyright term duration permitted by law in territory | G30: Maximum copyright term duration permitted by law in territory | H30: Maximum copyright term duration permitted by law in territory | I30: Maximum copyright term duration permitted by law in territory | J30: All rights, in all media, (excluding Theatrical). | K30: All rights, in all media, (excluding Theatrical). | L30: All rights, in all media, (excluding Theatrical). | M30: All rights, in all media, (excluding Theatrical). | N30: All rights, in all media, (excluding Theatrical). | O30: All rights, in all media, (excluding Theatrical).
F31: All rights, in all media, (excluding Theatrical). | G31: All rights, in all media, (excluding Theatrical). | H31: All rights, in all media, (excluding Theatrical). | I31: All rights, in all media, (excluding Theatrical).
B35: CLOSED CAPTIONING (CC) & HARD OF HEARING (HOH) SERVICES
D38: FEATURE | J38: EPISODIC
C39: Type of work | D39: THEATRICAL | F39: ALL CONTENT TYPES - HOME ENT/STREAMING Home Entertainment, Broadcast, SVOD, VOD… | H39: ALL CONTENT TYPES - LINEAR/BROADCAST Linear Broadcast Servicing Channel | J39: ALL CONTENT TYPES - HOME ENT/STREAMING Home Entertainment, Broadcast, SVOD, VOD… | L39: ALL CONTENT TYPES - LINEAR/BROADCAST Linear Broadcast servicing Channel | N39: DISCOVERY/NON-SCRIPTED
C40: SLA | D40: Standard+ | E40: Standard | F40: Standard+ | G40: Standard | H40: Standard + | I40: Standard | J40: Standard + | K40: Standard | L40: Standard + | M40: Standard | N40: Standard + | O40: Standard
C41: Turnaround Time in Calendar Days - Final Materials to vendor and Localized Content Delivery | D41: 6-9 days for Feature | E41: ≥ 10 days for Feature | F41: 6-9 days for Feature | G41: ≥ 10 days for Feature | H41: ≤ 6 calendar days | I41: ≥ 11 calendar days | J41: 2-5 calendar days for Episodic (from final) | K41: ≥ 6 calendar days for Episodic (Half Hour) | L41: 2- 5 calendar days | M41: ≥ 11 calendar days | N41: 2- 5 calendar days | O41: ≥ 11 calendar days
B42: Localization Function | C42: Activity | D42: Warner Media Consolidated Subtitling Rates Cards are based on the below service requirements
B43: SOURCE MATERIALS SUPPLIED FROM CLIENT | C43: Audio & Visual Content Prelim (Network, Locked) or Final (Low-Res or HD digital file; no physical) | D43: Prelim (if required) and Final AV Materials | E43: Final AV Materials | F43: Prelim (if required) and Final AV Materials | G43: Final AV Materials | H43: Prelim (if required) and Final AV Materials | I43: Final AV Materials | J43: Prelim (if required) and Final AV Materials | K43: Final AV Materials | L43: Prelim (if required) and Final AV Materials | M43: Final AV Materials | N43: Prelim (if required) and Final AV Materials | O43: Final AV Materials
C44: Scripts & Creative Documentation: Original Version Language (Ref Source Materials Definition Tab) | D44: Client to provide. If no English script or equivalent provided, additional charge may apply | E44: Client to provide. If no English script or equivalent provided, additional charge may apply | F44: Client to provide. If no English script or equivalent provided, additional charge may apply | G44: Client to provide. If no English script or equivalent provided, additional charge may apply | H44: Client to provide. If no English script or equivalent provided, additional charge may apply | I44: Client to provide. If no English script or equivalent provided, additional charge may apply | J44: Client to provide. If no English script or equivalent provided, additional charge may apply | K44: Client to provide. If no English script or equivalent provided, additional charge may apply | L44: Client to provide. If no English script or equivalent provided, additional charge may apply | M44: Client to provide. If no English script or equivalent provided, additional charge may apply | N44: Client to provide. If no English script or equivalent provided, additional charge may apply | O44: Client to provide. If no English script or equivalent provided, additional charge may apply
C45: Final Video Master When Video Master deliverable required | D45: Client to provide error free final video & audio, balanced M&E, textless at tail (if needed). Vendor to perform 3-point check QC upon receipt, noting issues within 48 hours | E45: Client to provide error free final video & audio, balanced M&E, textless at tail (if needed). Vendor to perform 3-point check QC upon receipt, noting issues within 48 hours | F45: Client to provide error free final video & audio, balanced M&E, textless at tail (if needed). Vendor to perform 3-point check QC upon receipt, noting issues within 48 hours | G45: Client to provide error free final video & audio, balanced M&E, textless at tail (if needed). Vendor to perform 3-point check QC upon receipt, noting issues within 48 hours | H45: Client to provide error free final video & audio, balanced M&E, textless at tail (if needed). Vendor to perform 3-point check QC upon receipt, noting issues within 48 hours | I45: Client to provide error free final video & audio, balanced M&E, textless at tail (if needed). Vendor to perform 3-point check QC upon receipt, noting issues within 48 hours | J45: Client to provide error free final video & audio, balanced M&E, textless at tail (if needed). Vendor to perform 3-point check QC upon receipt, noting issues within 48 hours | K45: Client to provide error free final video & audio, balanced M&E, textless at tail (if needed). Vendor to perform 3-point check QC upon receipt, noting issues within 48 hours | L45: Client to provide error free final video & audio, balanced M&E, textless at tail (if needed). Vendor to perform 3-point check QC upon receipt, noting issues within 48 hours | M45: Client to provide error free final video & audio, balanced M&E, textless at tail (if needed). Vendor to perform 3-point check QC upon receipt, noting issues within 48 hours | N45: Client to provide error free final video & audio, balanced M&E, textless at tail (if needed). Vendor to perform 3-point check QC upon receipt, noting issues within 48 hours | O45: Client to provide error free final video & audio, balanced M&E, textless at tail (if needed). Vendor to perform 3-point check QC upon receipt, noting issues within 48 hours
B46: SECURITY TIERS | C46: Applying security measures to Reference Materials (Ref Security Tiers Definition Tab) | D46: Tier MAX or 0. If Tier MAX required, additional charge may apply (security level to be discussed with client on each title) | E46: Tier MAX or 0. If Tier MAX required, additional charge may apply (security level to be discussed with client on each title) | F46: Vendor to provide secure access for translators / approvers to subtitling SaaS Platform. Additional watermarking must be applied by the system to ensure access is traceable to those granted access. | G46: Vendor to provide secure access for translators / approvers to subtitling SaaS Platform. Additional watermarking must be applied by the system to ensure access is traceable to those granted access. | H46: Vendor to provide secure access for translators / approvers to subtitling SaaS Platform. Additional watermarking must be applied by the system to ensure access is traceable to those granted access. | I46: Vendor to provide secure access for translators / approvers to subtitling SaaS Platform. Additional watermarking must be applied by the system to ensure access is traceable to those granted access. | J46: Vendor to provide secure access for translators / approvers to subtitling SaaS Platform. Additional watermarking must be applied by the system to ensure access is traceable to those granted access. | K46: Vendor to provide secure access for translators / approvers to subtitling SaaS Platform. Additional watermarking must be applied by the system to ensure access is traceable to those granted access. | L46: Vendor to provide secure access for translators / approvers to subtitling SaaS Platform. Additional watermarking must be applied by the system to ensure access is traceable to those granted access. | M46: Vendor to provide secure access for translators / approvers to subtitling SaaS Platform. Additional watermarking must be applied by the system to ensure access is traceable to those granted access. | N46: Vendor to provide secure access for translators / approvers to subtitling SaaS Platform. Additional watermarking must be applied by the system to ensure access is traceable to those granted access. | O46: Vendor to provide secure access for translators / approvers to subtitling SaaS Platform. Additional watermarking must be applied by the system to ensure access is traceable to those granted access.
B47: TRANSLATION | C47: Translator selection | D47: Vendor responsible for providing Native Speaker translator, client reserves the right to participate in translator selection. | E47: Vendor responsible for providing Native Speaker translator, client reserves the right to participate in translator selection | F47: Vendor responsible for providing Native Speaker translator, client reserves the right to participate in translator selection. | G47: Vendor responsible for providing Native Speaker translator, client reserves the right to participate in translator selection | H47: Vendor responsible for providing Native Speaker translator. | I47: Vendor responsible for providing Native Speaker translator. | J47: Vendor responsible for providing Native Speaker translator, client reserves the right to participate in translator selection. | K47: Vendor responsible for providing Native Speaker translator, client reserves the right to participate in translator selection | L47: Vendor responsible for providing Native Speaker translator. | M47: Vendor responsible for providing Native Speaker translator. | N47: Vendor responsible for providing Native Speaker translator. | O47: Vendor responsible for providing Native Speaker translator.
C48: Linguistic & Technical QC | D48: Native Speaker Linguistic QC & Full Linear Technical QC included. | E48: Native Speaker Linguistic QC & Full Linear Technical QC included. | F48: Native Speaker Linguistic QC & Full Linear Technical QC included. | G48: Native Speaker Linguistic QC & Full Linear Technical QC included. | H48: Linguistic QC possible at additional charge. Technical QC included | I48: Linguistic QC possible at additional charge. Technical QC included | J48: Native Speaker Linguistic QC & Full Linear Technical QC included. | K48: Native Speaker Linguistic QC & Full Linear Technical QC included. | L48: Linguistic QC possible at additional charge. Technical QC included | M48: Linguistic QC possible at additional charge. Technical QC included | N48: Linguistic QC possible at additional charge. Technical QC included | O48: Linguistic QC possible at additional charge. Technical QC included
C49: Compliance | D49: Censorship and / or softening of language for certain content may be required. Any potential sensitivities must be flagged to client, especially children's content. | E49: Censorship and / or softening of language for certain content may be required. Any potential sensitivities must be flagged to client, especially children's content. | F49: Censorship and / or softening of language for certain content may be required. Any potential sensitivities must be flagged to client, especially children's content. | G49: Censorship and / or softening of language for certain content may be required. Any potential sensitivities must be flagged to client, especially children's content. | H49: Censorship and / or softening of language for certain content may be required. Any potential sensitivities must be flagged to client, especially children's content. | I49: Censorship and / or softening of language for certain content may be required. Any potential sensitivities must be flagged to client, especially children's content. | J49: Censorship and / or softening of language for certain content may be required. Any potential sensitivities must be flagged to client, especially children's content. | K49: Censorship and / or softening of language for certain content may be required. Any potential sensitivities must be flagged to client, especially children's content. | L49: Censorship and / or softening of language for certain content may be required. Any potential sensitivities must be flagged to client, especially children's content. | M49: Censorship and / or softening of language for certain content may be required. Any potential sensitivities must be flagged to client, especially children's content. | N49: Censorship and / or softening of language for certain content may be required. Any potential sensitivities must be flagged to client, especially children's content. | O49: Censorship and / or softening of language for certain content may be required. Any potential sensitivities must be flagged to client, especially children's content.
C50: Translator's credit | D50: To be included on all subtitle files, unless client advises otherwise. | E50: To be included on all subtitle files, unless client advises otherwise. | F50: To be included on all subtitle files, unless client advises otherwise. | G50: To be included on all subtitle files, unless client advises otherwise. | H50: To be included on all subtitle files, unless client advises otherwise. | I50: To be included on all subtitle files, unless client advises otherwise. | J50: To be included on all subtitle files, unless client advises otherwise. | K50: To be included on all subtitle files, unless client advises otherwise. | L50: To be included on all subtitle files, unless client advises otherwise. | M50: To be included on all subtitle files, unless client advises otherwise. | N50: To be included on all subtitle files, unless client advises otherwise. | O50: To be included on all subtitle files, unless client advises otherwise.
B51: CLIENT APPROVAL | C51: Subtitles Approvals Non-Physical release | D51: Where client approvals are required, time for the approvals must be pre-agreed. If approvals are not received within agreed timelines, client is notified to determine next steps i.e extend deadline, proceed, etc | E51: Where client approvals are required, time for the approvals must be pre-agreed. If approvals are not received within agreed timelines, the timeline can be extended as appropriate and as agreed by both parties. | F51: Where client approvals are required, time for the approvals must be pre-agreed. If approvals are not received within agreed timelines, client is notified to determine next steps i.e extend deadline, proceed, etc | G51: Where client approvals are required, time for the approvals must be pre-agreed. If approvals are not received within agreed timelines, the timeline can be extended as appropriate and as agreed by both parties. | H51: No Client Approvals | I51: No Client Approvals | J51: Where client approvals are required, time for the approvals must be pre-agreed. If approvals are not received within agreed timelines, client is notified to determine next steps i.e extend deadline, proceed, etc | K51: Where client approvals are required, time for the approvals must be pre-agreed. If approvals are not received within agreed timelines, the timeline can be extended as appropriate and as agreed by both parties. Included in price. | L51: No Client Approvals | M51: No Client Approvals | N51: No Client Approvals | O51: No Client Approvals
C52: Subtitles Approvals Physical release | D52: Where client approvals are required, time for the approvals must be pre-agreed. If approvals are not received within agreed timelines, vendor notifies client to determine next steps i.e extend deadline, proceed, etc Included in price. All subs for Home Video release to be sent to the emulation QC vendor for pre-check before delivering to authoring. Pre-Delivery is done as XML with .BMP associated with content related media. | E52: Where client approvals are required, time for the approvals must be pre-agreed. If approvals are not received within agreed timelines, the timeline can be extended as appropriate and as agreed by both parties. Included in price. All subs for Home Video release to be sent to the emulation QC vendor for pre-check before delivering to authoring. Pre-Delivery is done as XML with .BMP associated with content related media. | F52: Where client approvals are required, time for the approvals must be pre-agreed. If approvals are not received within agreed timelines, vendor notifies client to determine next steps i.e extend deadline, proceed, etc Included in price. All subs for Home Video release to be sent to the emulation QC vendor for pre-check before delivering to authoring. Pre-Delivery is done as XML with .BMP associated with content related media. | G52: Where client approvals are required, time for the approvals must be pre-agreed. If approvals are not received within agreed timelines, the timeline can be extended as appropriate and as agreed by both parties. Included in price. All subs for Home Video release to be sent to the emulation QC vendor for pre-check before delivering to authoring. Pre-Delivery is done as XML with .BMP associated with content related media. | H52: No Client Approvals | I52: No Client Approvals | J52: Where client approvals are required, time for the approvals must be pre-agreed. If approvals are not received within agreed timelines, vendor notifies client to determine next steps i.e extend deadline, proceed, etc Included in price. | K52: Where client approvals are required, time for the approvals must be pre-agreed. If approvals are not received within agreed timelines, the timeline can be extended as appropriate and as agreed by both parties. Included in price. | L52: No Client Approvals | M52: No Client Approvals | N52: No Client Approvals | O52: No Client Approvals
B53: SONGS | C53: Songs Translation | D53: Plot pertinent and cleared lyrics will be subtitled If requested by Client | E53: Plot pertinent and cleared lyrics will be subtitled If requested by Client | F53: Plot pertinent and cleared lyrics will be subtitled If requested by Client | G53: Plot pertinent and cleared lyrics will be subtitled If requested by Client | H53: Plot pertinent and cleared lyrics will be subtitled If requested by Client | I53: Plot pertinent and cleared lyrics will be subtitled If requested by Client | J53: Plot pertinent and cleared lyrics will be subtitled If requested by Client | K53: Plot pertinent and cleared lyrics will be subtitled If requested by Client | L53: Plot pertinent and cleared lyrics will be subtitled If requested by Client | M53: Plot pertinent and cleared lyrics will be subtitled If requested by Client | N53: Plot pertinent and cleared lyrics will be subtitled If requested by Client | O53: Plot pertinent and cleared lyrics will be subtitled If requested by Client
B54: DELIVERABLES | C54: Format | D54: Includes one set of final deliverables to multiple end users, formats to be agreed with client. | E54: Includes one set of final deliverables to multiple end users, formats to be agreed with client. | F54: Includes one set of final deliverables to multiple end users, formats to be agreed with client. | G54: Includes one set of final deliverables to multiple end users, formats to be agreed with client. | H54: Includes one format file deliverables to one location. Additional charge for any more formats and multiple end users. | I54: Includes one set of final deliverables to multiple end users, formats to be agreed with client. | J54: Includes one set of final deliverables to multiple end users, formats to be agreed with client. | K54: Includes one set of final deliverables to multiple end users, formats to be agreed with client. | L54: Includes one set of final deliverables to multiple end users, formats to be agreed with client. | M54: Includes one set of final deliverables to multiple end users, formats to be agreed with client. | N54: Includes one set of final deliverables to multiple end users, formats to be agreed with client. | O54: Includes one set of final deliverables to multiple end users, formats to be agreed with client.
B55: ISSUES / REDELIVERIES | C55: Non-Physical release | D55: Vendor has an obligation to deliver accurate translated subtitle files, (this does not cover subjective difference). Egregious creative errors or technical errors must be remediated by vendor. | E55: Vendor has an obligation to deliver accurate translated subtitle files, (this does not cover subjective difference). Egregious creative errors or technical errors must be remediated by vendor. | F55: Vendor has an obligation to deliver accurate translated subtitle files, (this does not cover subjective difference). Egregious creative errors or technical errors must be remediated by vendor. | G55: Vendor has an obligation to deliver accurate translated subtitle files, (this does not cover subjective difference). Egregious creative errors or technical errors must be remediated by vendor. | H55: Vendor has an obligation to deliver accurate translated subtitle files, (this does not cover subjective difference). Egregious creative errors or technical errors must be remediated by vendor. | I55: Vendor has an obligation to deliver accurate translated subtitle files, (this does not cover subjective difference). Egregious creative errors or technical errors must be remediated by vendor. | J55: Vendor has an obligation to deliver accurate translated subtitle files, (this does not cover subjective difference). Egregious creative errors or technical errors must be remediated by vendor. | K55: Vendor has an obligation to deliver accurate translated subtitle files, (this does not cover subjective difference). Egregious creative errors or technical errors must be remediated by vendor. | L55: Vendor has an obligation to deliver accurate translated subtitle files, (this does not cover subjective difference). Egregious creative errors or technical errors must be remediated by vendor. | M55: Vendor has an obligation to deliver accurate translated subtitle files, (this does not cover subjective difference). Egregious creative errors or technical errors must be remediated by vendor. | N55: Vendor has an obligation to deliver accurate translated subtitle files, (this does not cover subjective difference). Egregious creative errors or technical errors must be remediated by vendor. | O55: Vendor has an obligation to deliver accurate translated subtitle files, (this does not cover subjective difference). Egregious creative errors or technical errors must be remediated by vendor.
C56: Physical release | D56: Upon receipt of QC report from 3rd party vendor, fixes will be redelivered within 48 hours. | E56: Upon receipt of QC report from 3rd party vendor, fixes will be redelivered within 48 hours. | F56: Upon receipt of QC report from 3rd party vendor, fixes will be redelivered within 48 hours. | G56: Upon receipt of QC report from 3rd party vendor, fixes will be redelivered within 48 hours. | H56: N/A | I56: N/A | J56: Upon receipt of QC report from 3rd party vendor, fixes will be redelivered within 48 hours. | K56: Upon receipt of QC report from 3rd party vendor, fixes will be redelivered within 48 hours. | L56: N/A | M56: N/A | N56: N/A | O56: N/A
B57: ARCHIVE/ BACK UP | C57: Additional deliverables | D57: Per WBD requirements. Additional charge may apply | E57: Per WBD requirements. Additional charge may apply | F57: Per WBD requirements. Additional charge may apply | G57: Per WBD requirements. Additional charge may apply | H57: Vendor Archive included | I57: Vendor Archive included | J57: Per WBD requirements. Additional charge may apply | K57: Per WBD requirements. Additional charge may apply | L57: Vendor Archive included | M57: Vendor Archive included | N57: Vendor Archive included | O57: Vendor Archive included
B58: BUYOUT RIGHTS | C58: Rights to be secured by vendor on behalf of WBD client | D58: All rights, all formats in perpetuity, theatrical rights included (or the equivalent legal requirements in each territory). | E58: All rights, all formats in perpetuity, theatrical rights included (or the equivalent legal requirements in each territory). | F58: Unrestricted. Theatrical rights not included. | G58: Unrestricted. Theatrical rights not included. | H58: Unrestricted. Theatrical rights not included. | I58: Unrestricted. Theatrical rights not included. | J58: Unrestricted. Theatrical rights not included. | K58: Unrestricted. Theatrical rights not included. | L58: Unrestricted. Theatrical rights not included. | M58: Unrestricted. Theatrical rights not included. | N58: Unrestricted. Theatrical rights not included. | O58: Unrestricted. Theatrical rights not included.
B61: DUBBING SERVICES
D64: FEATURE | J64: EPISODIC
C65: Type of work | D65: THEATRICAL | F65: NON-THEATRICAL | H65: NON-THEATRICAL LINEAR BROADCAST | J65: EPISODIC | M65: DISCOVERY / NON-SCRIPTED
C66: SLA | D66: Standard + | E66: Standard | F66: Standard + | G66: Standard | H66: Standard + | I66: Standard | J66: Standard + | K66: Standard | L66: Full Series or Batched Epsiodes | M66: Standard + | N66: Standard
C67: Single / Batch | D67: Single | E67: Single | F67: Single | G67: Single | H67: Single | I67: Single | J67: Single | K67: Single | L67: Batch | M67: Single | N67: Single
C68: Turnaround Time: Final Materials to vendor > Localized Content Delivery | D68: < 6 weeks | E68: > 6 weeks + | F68: < 6 weeks | G68: > 6 weeks + | H68: < 6 weeks | I68: > 6 weeks + | J68: < 7 calendar days | K68: > 8 calendar days | L68: > 28 days for for first batch delivery, cadence for balance of deliveries to be confirmed based on number of epsiodes | M68: 3-13 calendar days | N68: ≥ 14 calendar days
B69: Localization Function | C69: Activity | D69: WBD Consolidated Dubbing Rates Cards are based on the below service requirements
B70: ORDERING | C70: Content Description | D70: Feature Animation / Live Action | E70: Feature Animation / Live Action | F70: Feature Animation/ Live Action | G70: Feature Animation/ Live Action | H70: Feature Animation / Live Action | I70: Feature Animation / Live Action | J70: Episodic: single episode, accelerated, requiring non-final materials | K70: Episodic: single episode, may require prelim materials | L70: Working from final with episodes available at one time | M70: Episodic: single episode, may require prelim materials | N70: Episodic: single episode, may require prelim materials
B71: MATERIALS PROVIDED BY CLIENT & VENDOR'S EXPECTATIONS | C71: Audio Visual Content Prelim (Network, Locked) or Final (Low-Res or HD digital file) | D71: Locked Prelim and Final AV Materials (Note - addtional iterations can be can be provided by client if required) | E71: Locked Prelim (if required) and Final AV Materials. | F71: Locked Prelim and Final AV Materials (Note - Network can be provided by client if required) | G71: Locked Prelim and Final AV Materials | H71: Locked Prelim (if required) and Final AV Materials. | I71: Locked Prelim (if required) and Final AV Materials. | J71: Prelim (Network and / or Locked) and Final AV Materials | K71: Locked Prelim and Final AV Materials (Note - Network can be provided by client if required) | L71: Final AV Materials. (Note - Prelim can be provided by client if required) | M71: . Final AV Materials. Locked Prelim (where required). | N71: . Final AV Materials. Locked Prelim (where required).
C72: Audio Files: Print masters, Stems, and M&Es. Optionals, when available. | D72: Client to provide | E72: Client to provide | F72: Client to provide | G72: Client to provide | H72: Client to provide | I72: Client to provide | J72: Client to provide | K72: Client to provide | L72: Client to provide | M72: Client to provide | N72: Client to provide
C73: Scripts & Creative Documentation: Original Version Language (Ref Source Materials Definition Tab) | D73: Client to provide | E73: Client to provide | F73: Client to provide. Client may request vendor to create scripts at additional charge | G73: Client to provide. Client may request vendor to create scripts at additional charge | H73: Client to provide. Client may request vendor to create scripts at additional charge | I73: Client to provide. Client may request vendor to create scripts at additional charge | J73: Client to provide. Client may request vendor to create scripts at additional charge | K73: Client to provide. Client may request vendor to create scripts at additional charge | L73: Client to provide. Client may request vendor to create scripts at additional charge | M73: Client to provide. Client may request vendor to create scripts at additional charge | N73: Client to provide. Client may request vendor to create scripts at additional charge
C74: Key Names and Phrases Glossary Terms + Character Names | D74: OV English Glossary / KNP to be provided by client, if available. | E74: OV English Glossary / KNP to be provided by client, if available. | F74: OV English Glossary / KNP to be provided by client, if available. | G74: OV English Glossary / KNP to be provided by client, if available. | H74: OV English Glossary / KNP to be provided by client, if available. | I74: OV English Glossary / KNP to be provided by client, if available. | J74: OV English Glossary / KNP to be provided by client, if available. | K74: OV English Glossary / KNP to be provided by client, if available. | L74: OV English Glossary / KNP to be provided by client, if available. | M74: NA | N74: NA
C75: Metadata Title, Short synopsis, Long synopsis | D75: WBD to provide metadata template at the same timeframe as reference materials | E75: WBD to provide metadata template at the same timeframe as reference materials | F75: WBD to provide metadata template at the same timeframe as reference materials | G75: WBD to provide metadata template at the same timeframe as reference materials | H75: WBD to provide metadata template at the same timeframe as reference materials | I75: WBD to provide metadata template at the same timeframe as reference materials | J75: WBD to provide metadata template at the same timeframe as refererence materials | K75: WBD to provide metadata template at the same timeframe as reference materials | L75: WBD to provide metadata template at the same timeframe asreference materials | M75: NA | N75: NA
C76: Voice Testing VT Kit creation | D76: If required, WBD to provide Studio with voice tests kits. If not available, vendor can create for an additional charge. | E76: If required, WBD to provide Studio with voice tests kits. If not available, vendor can create for an additional charge. | F76: If required, WBD to provide Studio with voice tests kits. If not available, vendor can create for an additional charge. | G76: If required, WBD to provide Studio with voice tests kits. If not available, vendor can create for an additional charge. | H76: If required, WBD to provide Studio with voice tests kits. If not available, vendor can create for an additional charge. | I76: If required, WBD to provide Studio with voice tests kits. If not available, vendor can create for an additional charge. | J76: WBD to provide Studio with voice tests kits. If not available, vendor can create for an additional charge. | K76: WBD to provide Studio with voice tests kits. If not available, vendor can create for an additional charge. | L76: WBD to provide Studio with voice tests kits. If not available, vendor can create for an additional charge. | M76: NA | N76: NA
C77: Final Video Master When Video Master deliverable required | D77: Client to provide error free final video & audio, balanced M&E, textless at tail (if needed). Vendor to perform 3-point check QC upon receipt, noting issues within 48 hours | E77: Client to provide error free final video & audio, balanced M&E, textless at tail (if needed). Vendor to perform 3-point check QC upon receipt, noting issues within 48 hours | F77: Client to provide error free final video & audio, balanced M&E, textless at tail (if needed). Vendor to perform 3-point check QC upon receipt, noting issues within 48 hours | G77: Client to provide error free final video & audio, balanced M&E, textless at tail (if needed). Vendor to perform 3-point check QC upon receipt, noting issues within 48 hours | H77: Client to provide error free final video & audio, balanced M&E, textless at tail (if needed). Vendor to perform 3-point check QC upon receipt, noting issues within 48 hours | I77: Client to provide error free final video & audio, balanced M&E, textless at tail (if needed). Vendor to perform 3-point check QC upon receipt, noting issues within 48 hours | J77: Client to provide error free final video & audio, balanced M&E, textless at tail (if needed). Vendor to perform 3-point check QC upon receipt. | K77: Client to provide error free final video & audio, balanced M&E, textless at tail (if needed). Vendor to perform 3-point check QC upon receipt. | L77: Client to provide error free final video & audio, balanced M&E, textless at tail (if needed). Vendor to perform 3-point check QC upon receipt. | M77: NA | N77: NA
C78: Final Compliance Audio or/and Video Master When Compliance Master deliverable required | D78: N/A | E78: N/A | F78: N/A | G78: N/A | H78: N/A | I78: N/A | J78: Client to provide error free final video & audio, balanced M&E, textless at tail (if needed). Vendor to perform 3-point check QC upon receipt, noting issues within 48 hours | K78: Client to provide error free final video & audio, balanced M&E, textless at tail (if needed). Vendor to perform 3-point check QC upon receipt, noting issues within 48 hours | L78: Client to provide compliance error free final video or/ & audio, balanced M&E, textless at tail (if needed) 14 days prior delivery due date. Vendor to perform 3-point check QC upon receipt. | M78: NA | N78: NA
B79: SECURITY TIERS | C79: Applying security measures to Reference Materials (Ref Security Tiers Definition Tab) | D79: Tier MAX or 0. If Tier MAX required, additional charge may apply (security level to be discussed with client on each title) | E79: Tier MAX or 0. If Tier MAX required, additional charge may apply (security level to be discussed with client on each title) | F79: Tier 2 or 3. If Tier 1 required, additional charge may apply | G79: Tier 2 or 3. If Tier 1 required, additional charge may apply | H79: Tier 2 or 3. If Tier 1 required, additional charge may apply | I79: Tier 2 or 3. If Tier 1 required, additional charge may apply | J79: Tier 2 or 3. If Tier 1 required, additional charge may apply | K79: Tier 2 or 3. If Tier 1 required, additional charge may apply | L79: Tier 2 or 3. If Tier 1 required, additional charge may apply | M79: Tier 2 or 3. | N79: Tier 2 or 3.
B80: CLIENT APPROVAL RIGHTS | C80: Creative Localization Approvals (translated script, glossary, metadata, synopsis & screeners of final dub version for review) | D80: Where client approvals are required, time for the approvals must be pre-agreed. If approvals are not received within agreed timelines, the timeline can be extended as appropriate and as agreed by both parties. Additional cancellation fees may be charged in some circumstance. Included in price. | E80: Where client approvals are required, time for the approvals must be pre-agreed. If approvals are not received within agreed timelines, the timeline can be extended as appropriate and as agreed by both parties. Additional cancellation fees may be charged in some circumstance. Included in price. | F80: Where client approvals are required, time for the approvals must be pre-agreed. If approvals are not received within agreed timelines, the timeline can be extended as appropriate and as agreed by both parties. Additional cancellation fees may be charged in some circumstance. Included in price. | G80: Where client approvals are required, time for the approvals must be pre-agreed. If approvals are not received within agreed timelines, the timeline can be extended as appropriate and as agreed by both parties. Additional cancellation fees may be charged in some circumstance. Included in price. | H80: Where client approvals are required, time for the approvals must be pre-agreed. If approvals are not received within agreed timelines, the timeline can be extended as appropriate and as agreed by both parties. Additional cancellation fees may be charged in some circumstance. Included in price. | I80: Where client approvals are required, time for the approvals must be pre-agreed. If approvals are not received within agreed timelines, the timeline can be extended as appropriate and as agreed by both parties. Additional cancellation fees may be charged in some circumstance. Included in price. | J80: Where client approvals are required, time for the approvals must be pre-agreed. If approvals are not received within agreed timelines, the timeline can be extended as appropriate and as agreed by both parties. Additional cancellation fees may be charged in some circumstance. Included in price. | K80: Where client approvals are required, time for the approvals must be pre-agreed. If approvals are not received within agreed timelines, the timeline can be extended as appropriate and as agreed by both parties. Additional cancellation fees may be charged in some circumstance. Included in price. | L80: Where client approvals are required, time for the approvals must be pre-agreed. If approvals are not received within agreed timelines, the timeline can be extended as appropriate and as agreed by both parties. Additional cancellation fees may be charged in some circumstance. Included in price. | M80: Where client approvals are required, time for the approvals must be pre-agreed. If approvals are not received within agreed timelines, the timeline can be extended as appropriate and as agreed by both parties. Additional cancellation fees may be charged in some circumstance. Included in price. | N80: Where client approvals are required, time for the approvals must be pre-agreed. If approvals are not received within agreed timelines, the timeline can be extended as appropriate and as agreed by both parties. Additional cancellation fees may be charged in some circumstance. Included in price.
C81: Casting (VTK and Voice Sample requirements) | D81: Voice Samples included. Casting to VTK is an additional charge (max 3 tests per character, to be agreed at beginning of project) | E81: Voice Samples included. Casting to VTK is an additional charge (max 3 tests per character, to be agreed at beginning of project) | F81: Voice Samples may be requested and are included in price. Casting to VTK is an additional charge (max 3 tests per character, to be agreed at beginning of project) | G81: Voice Samples may be requested and are included in price. Casting to VTK is an additional charge (max 3 tests per character, to be agreed at beginning of project) | H81: Voice Samples may be requested and are included in price. Casting to VTK is an additional charge (max 3 tests per character, to be agreed at beginning of project) | I81: Voice Samples may be requested and are included in price. Casting to VTK is an additional charge (max 3 tests per character, to be agreed at beginning of project) | J81: Voice Samples included. Casting to VTK is an additional charge (max 3 tests per character, to be agreed at beginning of project) | K81: Voice Samples included. Casting to VTK is an additional charge (max 3 tests per character, to be agreed at beginning of project) | L81: Voice Samples included. Casting to VTK is an additional charge (max 3 tests per character, to be agreed at beginning of project) | M81: Voice approval may be requested, at client discretion. | N81: Voice approval may be requested, at client discretion.
C82: Star Talent Uplift | D82: Star Talent Uplift not included | E82: Star Talent Uplift not included | F82: Star Talent Uplift not included, can be additional charge. | G82: Star Talent Uplift not included, can be additional charge. | H82: Star Talent Uplift not included, can be additional charge. | I82: Star Talent Uplift not included, can be additional charge. | J82: Star Talent Uplift not included | K82: Star Talent Uplift not included | L82: Star Talent Uplift not included | M82: Star Talent may be requested by client, additional charge would apply. | N82: Star Talent may be requested by client, additional charge would apply.
C83: Child actors for child roles | D83: Child actors for child roles or vocals can be an additional charge. | E83: Child actors for child roles or vocals can be an additional charge. | F83: Child actors for child roles or vocals can be an additional charge. | G83: Child actors for child roles or vocals can be an additional charge. | H83: Child actors for child roles or vocals can be an additional charge. | I83: Child actors for child roles or vocals can be an additional charge. | J83: Child actors for child roles or vocals can be an additional charge. | K83: Child actors for child roles or vocals can be an additional charge. | L83: Child actors for child roles or vocals can be an additional charge. | M83: Child actors for child roles or vocals can be requested, additional charges would apply. | N83: Child actors for child roles or vocals can be requested, additional charges would apply.
C84: Recording Location (assuming in Territories) | D84: In territory, alternative location to be agreed and approved by WBD. If WBD require recording in a specific city location, uplifts may be applied | E84: In territory, alternative location to be agreed and approved by WBD. If WBD require recording in a specific city location, uplifts may be applied | F84: At vendor's discretion providing decision is transparent to WBD. If WBD require recording in a specific city location, uplifts may be applied | G84: At vendor's discretion providing decision is transparent to WBD. If WBD require recording in a specific city location, uplifts may be applied | H84: At vendor's discretion providing decision is transparent to WBD. If WBD require recording in a specific city location, uplifts may be applied | I84: At vendor's discretion providing decision is transparent to WBD. If WBD require recording in a specific city location, uplifts may be applied | J84: At vendor's discretion providing decision is transparent to WBD. If WBD require recording in a specific city location, uplifts may be applied | K84: At vendor's discretion providing decision is transparent to WBD. If WBD require recording in a specific city location, uplifts may be applied | L84: At vendor's discretion providing decision is transparent to WBD. If WBD require recording in a specific city location, uplifts may be applied | M84: At vendor's discretion providing decision is transparent to WBD. If WBD require recording in a specific city location, uplifts may be applied | N84: At vendor's discretion providing decision is transparent to WBD. If WBD require recording in a specific city location, uplifts may be applied
B85: NUMBER OF TALENTS | C85: Number of talents to be used for the content | D85: Local standard assumptions to be applied as to the number of dubbing actors needed for a project. | E85: Local standard assumptions to be applied as to the number of dubbing actors needed for a project. | F85: Local standard assumptions to be applied as to the number of dubbing actors needed for a project. | G85: Local standard assumptions to be applied as to the number of dubbing actors needed for a project. | H85: Local standard assumptions to be applied as to the number of dubbing actors needed for a project. | I85: Local standard assumptions to be applied as to the number of dubbing actors needed for a project. | J85: Local standard assumptions to be applied as to the number of dubbing actors needed for a project. | K85: Local standard assumptions to be applied as to the number of dubbing actors needed for a project. | L85: Local standard assumptions to be applied as to the number of dubbing actors needed for a project. | M85: Local standard assumptions to be applied as to the number of dubbing actors needed for a project. | N85: Local standard assumptions to be applied as to the number of dubbing actors needed for a project.
B86: LINE COUNT | C86: Number of lines (or loops) per min for the content that needs to be localized (Ref Line count Definition Tab) | D86: If over or under standard, additional charge or discount may apply | E86: If over or under standard, additional charge or discount may apply | F86: If over or under standard, additional charge or discount may apply | G86: If over or under standard, additional charge or discount may apply | H86: If over or under standard, additional charge or discount may apply | I86: If over or under standard, additional charge or discount may apply | J86: If over or under standard, additional charge or discount may apply | K86: If over or under standard, additional charge or discount may apply | L86: If over or under standard, additional charge or discount may apply | M86: If over or under standard, additional charge or discount may apply | N86: If over or under standard, additional charge or discount may apply
B87: SONGS (Songs Definition Tab) | C87: Opening Song Recording | D87: If requested by client and lyrics have been cleared for translation and dubbing. Additional charge. | E87: If requested by client and lyrics have been cleared for translation and dubbing. Additional charge. | F87: If requested by client and lyrics have been cleared for translation and dubbing. Additional charge. | G87: If requested by client and lyrics have been cleared for translation and dubbing. Additional charge. | H87: If requested by client and lyrics have been cleared for translation and dubbing. Additional charge. | I87: If requested by client and lyrics have been cleared for translation and dubbing. Additional charge. | J87: If requested by client and lyrics have been cleared for translation and dubbing. Additional charge. | K87: If requested by client and lyrics have been cleared for translation and dubbing. Additional charge. | L87: Included in all languages_x000D_ (Exception may apply) | M87: NA | N87: NA
C88: Songs Recording (within episode) | D88: If plot pertinent, and has both been requested by client and confirmation lyrics have been cleared for translation and dubbing. Additional charge. | E88: If plot pertinent, and has both been requested by client and confirmation lyrics have been cleared for translation and dubbing. Additional charge. | F88: If plot pertinent, and has both been requested by client and confirmation lyrics have been cleared for translation and dubbing. Additional charge. | G88: If plot pertinent, and has both been requested by client and confirmation lyrics have been cleared for translation and dubbing. Additional charge. | H88: If plot pertinent, and has both been requested by client and confirmation lyrics have been cleared for translation and dubbing. Additional charge. | I88: If plot pertinent, and has both been requested by client and confirmation lyrics have been cleared for translation and dubbing. Additional charge. | J88: If plot pertinent, and has both been requested by client and confirmation lyrics have been cleared for translation and dubbing. Additional charge. | K88: If plot pertinent, and has both been requested by client and confirmation lyrics have been cleared for translation and dubbing. Additional charge. | L88: If plot pertinent, and has both been requested by client and confirmation lyrics have been cleared for translation and dubbing. Additional charge. | M88: NA | N88: NA
B89: MIXING | C89: Mixing Type | D89: All mixing costs must be a separate line item in all pricing and bids. 5.1 & 7.1 included. Additional charge for ATMOS if requested. | E89: All mixing costs must be a separate line item in all pricing and bids. 5.1 & 7.1 included. Additional charge for ATMOS if requested. | F89: All mixing costs must be a separate line item in all pricing and bids. 2.0 & 5.1 included. Additional charge for ATMOS if requested. | G89: All mixing costs must be a separate line item in all pricing and bids. 2.0 & 5.1 included. Additional charge for ATMOS if requested. | H89: All mixing costs must be a separate line item in all pricing and bids. 2.0 & 5.1 included. Additional charge for ATMOS if requested. | I89: All mixing costs must be a separate line item in all pricing and bids. 2.0 & 5.1 included. Additional charge for ATMOS if requested. | J89: 2.0 & 5.1 | K89: 2.0 & 5.1 | L89: 2.0 & 5.1 | M89: 2.0 / Stereo Only. If 5.1 required, must be requested and agreed at the start of a project. | N89: 2.0 / Stereo Only. If 5.1 required, must be requested and agreed at the start of a project.
C90: Mixing Location | D90: Mixing location will be at vendor's discretion providing decision is transparent to WBD, if WBD require mixing in a specific location, uplifts may be applied. WBD may designate mixing be done by a separate company, or internally to WBD. | E90: Mixing location will be at vendor's discretion providing decision is transparent to WBD, if WBD require mixing in a specific location, uplifts may be applied. WBD may designate mixing be done by a separate company, or internally to WBD. | F90: Mixing location will be at vendor's discretion providing decision is transparent to WBD, if WBD require mixing in a specific location, uplifts may be applied. WBD may designate mixing be done by a separate company, or internally to WBD. | G90: Mixing location will be at vendor's discretion providing decision is transparent to WBD, if WBD require mixing in a specific location, uplifts may be applied. WBD may designate mixing be done by a separate company, or internally to WBD. | H90: Mixing location will be at vendor's discretion providing decision is transparent to WBD, if WBD require mixing in a specific location, uplifts may be applied. WBD may designate mixing be done by a separate company, or internally to WBD. | I90: Mixing location will be at vendor's discretion providing decision is transparent to WBD, if WBD require mixing in a specific location, uplifts may be applied. WBD may designate mixing be done by a separate company, or internally to WBD. | J90: At vendor's discretion providing decision is transparent to WBD. If WBD require mixing in a specific location, uplifts may be applied | K90: At vendor's discretion providing decision is transparent to WBD. If WBD require mixing in a specific location, uplifts may be applied | L90: At vendor's discretion providing decision is transparent to WBD. If WBD require mixing in a specific location, uplifts may be applied | M90: At vendor's discretion providing decision is transparent to WBD. If WBD require mixing in a specific location, uplifts may be applied | N90: At vendor's discretion providing decision is transparent to WBD. If WBD require mixing in a specific location, uplifts may be applied
B91: DELIVERABLES | C91: Audio File Delivery; i.e. to Digital Cinema Lab & DETE | D91: Vendor to deliver audio file to WBD agreed specification | E91: Vendor to deliver audio file to WBD agreed specification | F91: Vendor to deliver audio file to WBD agreed specification | G91: Vendor to deliver audio file to WBD agreed specification | H91: Vendor to deliver audio file to WBD agreed specification | I91: Vendor to deliver audio file to WBD agreed specification | J91: Vendor to deliver audio file to WBD agreed specification | K91: Vendor to deliver audio file to WBD agreed specification | L91: Vendor to deliver audio file to WBD agreed specification | M91: Vendor to deliver audio file to WBD agreed specification | N91: Vendor to deliver audio file to WBD agreed specification
C92: Script & Insert Report; i.e. to WBD & NEST | D92: Vendor to provide as recorded script & translated insert report | E92: Vendor to provide as recorded script & translated insert report | F92: Vendor to provide as recorded script & translated insert report | G92: Vendor to provide as recorded script & translated insert report | H92: Vendor to provide as recorded script & translated insert report | I92: Vendor to provide as recorded script & translated insert report | J92: Vendor to provide as recorded script & translated insert report | K92: Vendor to provide as recorded script & translated insert report | L92: Vendor to provide as recorded script & translated insert report | M92: Vendor to provide as recorded script & translated insert report | N92: Vendor to provide as recorded script & translated insert report
C93: Key Names and Phrases Glossary Terms + Character Names | D93: Localized Translated KNP included | E93: Localized Translated KNP included | F93: Vendor to provide Localized Translated KNP. | G93: Vendor to provide Localized Translated KNP. | H93: Vendor to provide Localized Translated KNP. | I93: Vendor to provide Localized Translated KNP. | J93: Localized Translated KNP included | K93: Localized Translated KNP included | L93: Localized Translated KNP included | M93: Vendor to provide Localized Translated KNP. | N93: Vendor to provide Localized Translated KNP.
C94: Metadata Episode title, short episode synopsis, season synopsis. | D94: Metadata translation included at no additional charge if Metadata available within the same timeframe as scripts | E94: Metadata translation included at no additional charge if Metadata available within the same timeframe as scripts | F94: Metadata translation included at no additional charge if Metadata available within the same timeframe as scripts | G94: Metadata translation included at no additional charge if Metadata available within the same timeframe as scripts | H94: Metadata translation included at no additional charge if Metadata available within the same timeframe as scripts | I94: Metadata translation included at no additional charge if Metadata available within the same timeframe as scripts | J94: Metadata translation included at no additional charge if Metadata available within the same timeframe as reference materials | K94: Metadata translation included at no additional charge if Metadata available within the same timeframe as reference materials | L94: Metadata translation included at no additional charge if Metadata available within the same timeframe as reference materials | M94: Upon request, metadata translation can be included at no additional charge if Metadata available within the same timeframe as reference materials | N94: Upon request, metadata translation can be included at no additional charge if Metadata available within the same timeframe as reference materials
C95: Dub card/Credit list Creation | D95: Dub card/Credit list as a text based format or graphic card per territory requirements. Additional charge for requests made after completion of the language | E95: Dub card/Credit list as a text based format or graphic card per territory requirements. Additional charge for requests made after completion of the language | F95: Dub card/Credit list as a text based format or graphic card per territory requirements. Additional charge for requests made after completion of the language | G95: Dub card/Credit list as a text based format or graphic card per territory requirements. Additional charge for requests made after completion of the language | H95: Dub card/Credit list as a text based format or graphic card per territory requirements. Additional charge for requests made after completion of the language | I95: Dub card/Credit list as a text based format or graphic card per territory requirements. Additional charge for requests made after completion of the language | J95: Dub card/Credit list as a text based format or graphic card per territory requirements. Additional charge for Video or requests made after completion of language. | K95: Dub Card / Credit list as a text based format or graphic card per territory requirements. Additional charge may be applied for requests made after completion of language. | L95: Dub Card / Credit list as a text based format or graphic card per territory requirements. Additional charge may be applied for requests made after completion of language. | M95: Dub Card / Credit list as a text based format or graphic card per territory requirements. Additional charge may be applied for requests made after completion of language. | N95: Dub Card / Credit list as a text based format or graphic card per territory requirements. Additional charge may be applied for requests made after completion of language.
C96: AOR - Assignment of Rights | D96: Vendor must secure all signatures on AORs and deliver to WBD as physical or scanned documents at completion of project or upon request. | E96: Vendor must secure all signatures on AORs and deliver to WBD as physical or scanned documents at completion of project or upon request. | F96: Vendor must secure all signatures on AORs and deliver to WBD as physical or scanned documents at completion of project or upon request. | G96: Vendor must secure all signatures on AORs and deliver to WBD as physical or scanned documents at completion of project or upon request. | H96: Vendor must secure all signatures on AORs and deliver to WBD as physical or scanned documents at completion of project or upon request. | I96: Vendor must secure all signatures on AORs and deliver to WBD as physical or scanned documents at completion of project or upon request. | J96: Vendor shall gather all signatures on AORs and be able to deliver to WBD as physical or scanned documents upon request | K96: Vendor shall gather all signatures on AORs and be able to deliver to WBD as physical or scanned documents upon request | L96: Vendor shall gather all signatures on AORs and be able to deliver to WBD as physical or scanned documents upon request | M96: Vendor shall gather all signatures on AORs and be able to deliver to WBD as physical or scanned documents upon request | N96: Vendor shall gather all signatures on AORs and be able to deliver to WBD as physical or scanned documents upon request
B97: BUYOUT RIGHTS & DURATION | C97: Duration Localization vendor must secured on behalf of WBD | D97: Maximum copyright term duration permitted by law in territory | E97: Maximum copyright term duration permitted by law in territory | F97: Maximum copyright term duration permitted by law in territory | G97: Maximum copyright term duration permitted by law in territory | H97: Maximum copyright term duration permitted by law in territory | I97: Maximum copyright term duration permitted by law in territory | J97: Maximum copyright term duration permitted by law in territory | K97: Maximum copyright term duration permitted by law in territory | L97: Maximum copyright term duration permitted by law in territory | M97: Maximum copyright term duration permitted by law in territory | N97: Maximum copyright term duration permitted by law in territory
C98: Rights Localization vendor must secured on behalf of WBD | D98: All rights, all formats in perpetuity, theatrical rights included (or the equivalent legal requirements in each territory). | E98: All rights, all formats in perpetuity, theatrical rights included (or the equivalent legal requirements in each territory). | F98: All rights, in all media, (excluding Theatrical). | G98: All rights, in all media, (excluding Theatrical). | H98: All rights, in all media, (excluding Theatrical). | I98: All rights, in all media, (excluding Theatrical). | J98: All rights, in all media, (excluding Theatrical). | K98: All rights, in all media, (excluding Theatrical). | L98: All rights, in all media, (excluding Theatrical). | M98: All rights, in all media, (excluding Theatrical). | N98: All rights, in all media, (excluding Theatrical).
B99: ARCHIVE/ BACK UP | C99: Final Protools session, Screeners, Dialogue Stems… | D99: Per WBD requirements. | E99: Per WBD requirements. | F99: Per WBD requirements. Additional charge may apply | G99: To be agreed with WBD per project. Additional charge may apply | H99: Per WBD requirements. Additional charge may apply | I99: To be agreed with WBD per project. Additional charge may apply | J99: Per WBD requirements. | K99: Per WBD requirements. | L99: Per WBD requirements. | M99: Vendor archive included | N99: Vendor archive included
B102: AUDIO DESCRIPTION SERVICES
D105: FEATURE | J105: EPISODIC
C106: Type of work | D106: THEATRICAL | F106: NON-THEATRICAL | H106: NON-THEATRICAL LINEAR BROADCAST | J106: EPISODIC | M106: DISCOVERY / NON-SCRIPTED
C107: SLA | D107: Standard + | E107: Standard | F107: Standard + | G107: Standard | H107: Standard + | I107: Standard | J107: Standard + | K107: Standard | L107: Full Series or Batched Epsiodes | M107: Standard
C108: Single / Batch | D108: Single | E108: Single | F108: Single | G108: Single | H108: Single | I108: Single | J108: Single | K108: Single | L108: Batch | M108: Single
C109: Turnaround Time: Final Materials to vendor > Localized Content Delivery | D109: < 6weeks | E109: > 6 weeks + | F109: < 6weeks | G109: > 6 weeks + | H109: < 6weeks | I109: > 6 weeks + | J109: < 7 calendar days | K109: >= 8 calendar days | L109: >= 28 days for for first batch delivery, cadence for balance of deliveries to be confirmed based on number of epsiodes | M109: ≥ 14 calendar days
B110: Localization Function | C110: Activity | D110: WBD Consolidated Rates Cards are based on the below service requirements
B111: ORDERING | C111: Content Description | D111: Feature Animation/ Live Action | E111: Feature Animation/ Live Action | F111: Feature Animation/ Live Action | G111: Feature Animation/ Live Action | H111: Feature Animation/ Live Action | I111: Feature Animation/ Live Action | J111: Episodic: single episode, accelerated, requiring non-final materials | K111: Episodic: single episode, may require prelim materials | L111: Working from final with episodes available at one time | M111: Episodic: single episode, Work from final
B112: MATERIALS PROVIDED BY CLIENT & VENDOR'S EXPECTATIONS | C112: Audio Visual Content Prelim (Network, Locked) or Final (Low-Res or HD digital file) | D112: Locked Prelim and Final AV Materials (Note - Network can be provided by client if required) | E112: Locked Prelim and Final AV Materials | F112: Locked Prelim and Final AV Materials (Note - Network can be provided by client if required) | G112: Locked Prelim and Final AV Materials | H112: Locked Prelim and Final AV Materials (Note - Network can be provided by client if required) | I112: Final AV Materials | J112: Prelim (Network and / or Locked) and Final AV Materials | K112: Locked Prelim and Final AV Materials (Note - Network can be provided by client if required) | L112: Final AV Materials. (Note - Prelim can be provided by client if required) | M112: Final AV Materials
C113: Audio Files: Print masters | D113: Client to provide | E113: Client to provide | F113: Client to provide | G113: Client to provide | H113: Client to provide | I113: Client to provide | J113: Client to provide | K113: Client to provide | L113: Client to provide | M113: Client to provide
C114: Scripts & Creative Documentation: Original Language Version and/or Localized Version Script where applicable (Ref Source Materials Definition Tab) | D114: Client to provide | E114: Client to provide | F114: Client to provide | G114: Client to provide | H114: Client to provide | I114: Client to provide | J114: Client to provide | K114: Client to provide | L114: Client to provide | M114: Client to provide.
C115: Key Names and Phrases Glossary Terms + Character Names | D115: Client to provide when available | E115: Client to provide when available | F115: Client to provide when available | G115: Client to provide when available | H115: Client to provide when available | I115: Client to provide when available | J115: Client to provide when available | K115: Client to provide when available | L115: Client to provide when available | M115: N/A
C116: Metadata Title, Short synopsis, Long synopsis | D116: WBD to provide metadata template at the same timeframe as reference materials | E116: WBD to provide metadata template at the same timeframe as reference materials | F116: N/A | G116: N/A | H116: N/A | I116: N/A | J116: WBD to provide metadata template at the same timeframe as refererence materials | K116: WBD to provide metadata template at the same timeframe as reference materials | L116: WBD to provide metadata template at the same timeframe asreference materials | M116: N/A
C117: Voice Testing VT Kit creation | D117: N/A | E117: N/A | F117: N/A | G117: N/A | H117: N/A | I117: N/A | J117: N/A | K117: N/A | L117: N/A | M117: N/A
C118: Final Video Master When Video Master deliverable required | D118: N/A | E118: N/A | F118: N/A | G118: N/A | H118: N/A | I118: N/A | J118: N/A | K118: N/A | L118: N/A | M118: N/A
C119: Final Compliance Audio or/and Video Master When Compliance Master deliverable required | D119: N/A | E119: N/A | F119: N/A | G119: N/A | H119: N/A | I119: N/A | J119: N/A | K119: N/A | L119: N/A | M119: N/A
...

Sheet Definitions
B2: WBD GCO Localization RFP - Definitions
B3: Below are relevant definitions for localization functions outlined in Column B in the SLAs tab.
B5: SOURCE MATERIALS DEFINITION
B7: Source materials | C7: Description
B8: Video format (digital delivery) | C8: ProRes, MP4, MOV, MPEG, MXF
B9: Preliminary cut - network cut | C9: “Network cut” or “Rough cut” - An early assemblage of non-final content. Scenes can be changed (edited out, shortened, removed). VFX, color, dialogue, sound mix and titles / credits are all “Temp” and subject to change. This is usually to give the translator a heads-up in time for the translation and a visual reference. They may not use it to start their translation as content can be changed, but it helps them to go faster in the translation. This version is usually used only for translators and giving the first idea of casting.
B10: Preliminary cut - locked cut | C10: "Locked cut" or “Picture lock” - In general, changes to program cut have been done and approved (timeline of the content is set aka Picture timing is locked). Dialogue is locked in, number of actors is set, M&E may not be available at that time. ADR may still happen later on, final music might change, Final visuals may not be available & main graphic text info may or may not be included.
B11: Final cut | C11: Error free final video & audio, balanced M&E, textless at tail (if needed)
B12: Audio files | C12: Print masters, Stems and M&Es
B13: Non-Production English script format assumptions: (client will always provide best available) | C13: Full transcription, characters speaking & TC (can be annotated or not) ideally will include: -Cast List -Identify Cast played by Children -Titles List -Synopsis -Key Glossary -Subtitle for foreign dialogue when needed -All Inserts -Songs -Line Count Per Character
B14: Lyrics and lead sheets | C14: Note - these typically are provided by Production
B15: Title lists | C15: Can be requested as a separate deliverable to the script
B16: Character lists | C16: Can be requested as a separate deliverable to the script
B17: Character line counts | C17: Can be requested as a separate deliverable to the script
B18: Run time (minutes) | C18: Total billable runtime so align to active program content i.e. should not be inclusive of leaders/tails/textless sections of the source material. Total Runtime should be measured in minutes and rounded up/down to the closest minute.
B21: TURNAROUND DEFINITION
C23: Description
B24: Turnaround | C24: Turnaround is defined as the time period from receipt of all error-free Source Materials (to delivery of the Final Delivery Materials. For this purpose a “day” is a calendar day that is not a public holiday or weekend in the territory of the target language.
C26: Turnaround shall be counted on the day of receipt of all Source Materials if the Source Material is received by Company before 12:00 PM; if the Source Materials are received after 12:00 PM, the turnaround shall be counted from the following day, and if the day of receipt of Source Materials is the day prior to a vendor public holiday, turnaround shall be counted from the day of receipt only if the Source Materials are received before 9:00 AM.
B28: SECURITY TIERS DEFINITION
C30: Tier 3 | D30: Tier 2 | E30: Tier 1, 0, MAX
B31: Description | C31: Standard | D31: High | E31: Franchise
B32: Type of content | C32: Catalogue/Post-air (Broadcast)/ Post-digital Release (Theatrical) | D32: Pre-release episodic and Pre-Release Theatrical content | E32: Highest Security, i.e. tent pole titles
B33: Reference material watermarking (proxies and scripts) | C33: -ID per destination/user -Visibly watermarked | D33: -ID per destination/user -Visibly watermarked -A/V forensically watermarked | E33: -ID per destination/user -Visibly watermarked -A/V forensically watermarked
B34: Security requirements | C34: -WBD Vendor Risk Management Assessment -Compliance with WBD Data & Content Security Addendum | D34: -TPN or WBD Content Security remote assessment to ensure compliance with MPA Best Practices -Translation work must take place via an approved platform (vs. working locally with materials) -Compliance with WBD Data & Content Security Addendum | E34: -TPN or WBD Content Security on-site assessment to ensure compliance with MPA Best Practices -Translation work must take place on-site -Compliance with WBD Data & Content Security Addendum
E35: (Tier 0, Max security level to be discussed with client on each title)
B37: SONGS DEFINITION
B39: Songs definition | C39: Description
B40: Ditty recorded as dialogue (no charge) | C40: It requires little musical ability or direction and can be recorded with the ADR. It does not require extra time in the recordings, vocal director, and lyricist. In most cases, we would expect the ditty to be a capella and to last around 2 - 5 seconds. Example of standard ditties: humming, ‘la-la-la’; ‘ta-ta-taaaa’ ; ‘Good Mooorning’ Exceptions Exceptions are applied based on local market practice.
B41: Ditty (charge as extra) | C41: A ditty is easily learned and should not require a lead sheet since ditties are often ad-libbed in character by the voice actor (e.g. a familiar children’s song). Ditty with more than one singer - Same as above but is ad-libbed among all performers. This type of song is unstructured and free of specific harmonies and does not require great musical sensibilities (e.g. a group of people singing in a pub). The key aspect of a ditty is that it is technically and creatively less complex than a vocal; we would generally expect them to be a aapella but on occasion there may also be instrumental accompaniment. There is usually not a requirement for a music director or lyricist. Exceptions Exceptions are applied based on local market practice.
B42: Vocal - solo | C42: A song which has a structured and specific melody with defined lyrics (very often with rhymes) which will normally require lead sheets and has an instrumental accompaniment; the vocal performer should have some talent for singing. This vocal can often be sung in-character, or maybe a song that is sung-over the action by a non-character performer. The expectation is that a vocal will be at least 20 seconds or shorter, subject to complexity. This song requires a lyricist and musical director.
B43: Vocal - 2 lead singers | C43: Vocal with 2 lead performers - description as above.
B44: Vocal - with chorus | C44: Lead Vocal with Backing Vocals - Same as above but is performed with additional background singers.
B46: General Cartoon Network rules | C46: Notes
B47: Main title / opening song | C47: Always dubbed, once then re-use to the other episodes, if the main title song has variations then the dubbing needs to be updated. Opening Songs are on average between 30-60 seconds.
B48: Background & commercial songs | C48: Never dubbed
B49: Songs not important to plot | C49: Local client's decision
B50: End credit song | C50: Local client's decision
B51: Talent | C51: Wherever possible, studios should use the cheaper option between using singers, voice actor talent
B54: BATCH SIZE DEFINITION
B56: Series
B57: Batch sizes assumption | C57: Current season | D57: Catalogue
C58: Batch of 110 Animation Batch of 180 mins Live Action | D58: Batch of up to 600 mins
B59: SLA comment | C59: 110 min for Animation 180min for Live action Assumes vendor works from final | D59: Assumes vendor works from final. Based on staggered delivery
B60: SLA | C60: Standard Batch | D60: Catalogue
B61: Single/Batch | C61: Batch | D61: Batch - Full Series
B62: Turnaround in calendar days | C62: 28 - 56 days** | D62: 84 days**
B63: Exceptions | C63: Exceptions are applied based on local market practice | D63: Exceptions are applied based on local market practice
B64: Other | C64: if Kids required for a short turnaround, detailed schedule is needed - Kids following government permission | D64: if Kids required for a short turnaround, detailed schedule is needed - Kids following government permission
B67: LINE COUNT DEFINITION
B69: Line count | C69: Lines per minute average | D69: Examples
B70: High | C70: 19+ lines per minute average | D70: Example titles charged with an uplift for HBO:​ The Deuce (60) - 435 takes​ The Plot Against America (60) ~ 436 takes ​ Turner French uplift for series average of over 360 lines per 22 min episode (over 16 per min)​
B71: Standard | C71: 11 - 18 lines per minute average
B72: Low | C72: Less than 10 lines per minute average | D72: Tom & Jerry, Mighty Mike
